Workbook

Sheet Sheet1
B1: Previous Analyst | C1: (All)
B2: Months (Last PR date) | C2: (Multiple Items)
B4: Name | C4: Email | D4: Last PR date
B5: Prashanth Poultry Private Limited | C5: prashanthpoultry@gmail.com | D5: 45901
B6: Acute retail Infra Private Limited | C6: alok.tiwary@futuregroup.in | D6: 45940
B7: Aditya Auto Industries | C7: bdm@apipl.co.in | D7: 45960
B8: Advanced Computers & Mobiles India Private Limited | C8: tushar.jagtap@advancedmobile.in | D8: 45940
B9: Aisshpra Life Spaces | C9: grvmht10@gmail.com, ayush@ayushandassociates.com | D9: 45945
B10: Aventura Components Private Limited | C10: sghosh@ewgroup.in | D10: 45946
B11: Bhakti Extractions Private Limited | C11: Mr. Atul Mantri <bhaktisoya@gmail.com> | D11: 45946
B12: Callac Poly Exim Private Limited | C12: ravindracallacpoly@gmail.com | D12: 45917
B13: Chintpurni Steel Private | C13: cspl2005@yahoo.com | D13: 45947
B14: Compuage Infocom Limited | C14: Ms. Anmol jolly <anmol.jolly@compuageindia.com> | D14: 45957
B15: DCX Systems Ltd | C15: sk@dcxindia.com | D15: 45919
B16: Earth Water Limited | C16: sghosh@ewgroup.in | D16: 45946
... B52: Zandros Granitos LLP | C52: zandrosgranito@gmail.com | D52: 45922

Sheet ALL
A1: =TODAY() -> 46316 | B1: Done | C1: Name | D1: Amount | E1: Date of becoming INC | F1: Previous Analyst | G1: Group Head | H1: Last PR date | I1: LT Rating | J1: ST Rating | K1: Last Date | L1: Contact Person | M1: Number | N1: Email | O1: =TODAY() -> 46316 | P1: BD | Q1: Committee Date | R1: Transfer | U1: Lt | V1: St
A2: =IF(I2="Withdrawn",,($A$1-H2)-365) -> 12 | B2: FALSE | C2: Harman Finochem Limited | D2: 60 | F2: Palak Dand | G2: Sudarshan Shreenivas | H2: 45939 | I2: IVR B /Negative; INC | J2: IVR A4; INC | K2: =EDATE(H2,12) -> 46304 | N2: rupesh@harmanfinochem.com | Q2: 46310 | U2: IVR A- /Negative; INC | V2: IVR A4+; INC
A3: =IF(I3="Withdrawn",,($A$1-H3)-365) -> 11 | B3: FALSE | C3: Acute retail Infra Private Limited | D3: 60.11 | F3: Srushti Patil | G3: Sudarshan Shreenivas | H3: 45940 | I3: IVR D; INC | K3: =EDATE(H3,12) -> 46305 | L3: Mr. Alok Tiwary-7498603458 | N3: alok.tiwary@futuregroup.in | Q3: 46310 | U3: IVR BB+ /Negative; INC | V3: IVR A4+(CE); INC
A4: =IF(I4="Withdrawn",,($A$1-H4)-365) -> 11 | B4: FALSE | C4: Advanced Computers & Mobiles India Private Limited | D4: 200 | F4: Srushti Patil | G4: Sudarshan Shreenivas | H4: 45940 | I4: IVR D; INC | J4: IVR D; INC | K4: =EDATE(H4,12) -> 46305 | L4: Tushar Jagtap-7045695474 | N4: tushar.jagtap@advancedmobile.in | Q4: 46310 | U4: IVR BB /Negative; INC | V4: IVR A4(CE); INC
A5: =IF(I5="Withdrawn",,($A$1-H5)-365) -> 7 | B5: FALSE | C5: Grand Canyon SEZ Private Limited | D5: 283.03 | F5: Palak Dand | G5: Sudarshan Shreenivas | H5: 45944 | I5: IVR BB /Negative; INC | K5: =EDATE(H5,12) -> 46309 | N5: archit.bartaria@asfinfrastructure.com, dinesh.jain@asfinfrastructure.com, prannoy.kumar@asfinfrastructure.com | Q5: 46310 | U5: IVR BB(CE) /Negative; INC | V5: IVR A4; INC
A6: =IF(I6="Withdrawn",,($A$1-H6)-365) -> 2 | B6: FALSE | C6: Aisshpra Life Spaces | D6: 86 | E6: 45097 | F6: Sonal Ghanchi | G6: Amey Joshi | H6: 45949 | I6: IVR B+ /Negative; INC | K6: =EDATE(H6,12) -> 46314 | L6: - | M6: - | N6: grvmht10@gmail.com, ayush@ayushandassociates.com | Q6: 46310 | U6: IVR BB- /Negative; INC | V6: IVR D; INC
A7: =IF(OR(I7="Withdrawn",R7="Transfer"),"",($A$1-H7)-365) -> 5 | B7: FALSE | C7: Aventura Components Private Limited | D7: 95 | E7: 44257 | F7: Sonal Ghanchi | G7: Amey Joshi | H7: 45946 | I7: IVR D; INC | J7: IVR D; INC | K7: =EDATE(H7,12) -> 46311 | L7: Kuldip Maity | M7: 9830353213 | N7: sghosh@ewgroup.in | Q7: 46310 | U7: IVR BB-(CE) /Negative; INC | V7: Withdrawn
A8: =IF(OR(I8="Withdrawn",R8="Transfer"),"",($A$1-H8)-365) -> 5 | B8: FALSE | C8: M/S Idupulapadu Cotton Mills Private Limited | D8: 275 | E8: 45207 | F8: Rajsee Warang | G8: Amey Joshi | H8: 45946 | I8: IVR B /Negative; INC | J8: IVR A4; INC | K8: =EDATE(H8,12) -> 46311 | L8: - | M8: - | N8: M SITARAMAIAH <info@icmtex.com> | Q8: 46310 | U8: IVR B+ /Negative; INC
A9: =IF(OR(I9="Withdrawn",R9="Transfer"),"",($A$1-H9)-365) -> 5 | B9: FALSE | C9: Raghava Constructions India Private Limited | D9: 750 | E9: 3/22/2021 | F9: Rajsee Warang | G9: Amey Joshi | H9: 45946 | I9: IVR B /Negative; INC | J9: IVR A4; INC | K9: =EDATE(H9,12) -> 46311 | L9: - | M9: - | N9: raghava.constructions@gmail.com | Q9: 46310 | U9: IVR B /Negative; INC
A10: =IF(OR(I10="Withdrawn",R10="Transfer"),"",($A$1-H10)-365) -> 5 | B10: FALSE | C10: Renuka Realtors | D10: 250 | E10: 8/22/2023 | F10: Rajsee Warang | G10: Amey Joshi | H10: 45946 | I10: IVR C+ /Negative; INC | K10: =EDATE(H10,12) -> 46311 | L10: Ganpathy | M10: 9892984465 | N10: archit@ruparel.in | Q10: 46310 | U10: IVR B- /Negative; INC
A11: =IF(OR(I11="Withdrawn",R11="Transfer"),"",($A$1-H11)-365) | B11: FALSE | C11: Earth Water Limited | D11: 166 | E11: 44257 | F11: Sonal Ghanchi | G11: Amey Joshi | H11: 45946 | I11: IVR D; INC | K11: =EDATE(H11,12) -> 46311 | L11: Sonal Bajaj | M11: 9920769591 | N11: sghosh@ewgroup.in | R11: Transfer | U11: IVR C+ /Negative; INC
A12: =IF(OR(I12="Withdrawn",R12="Transfer"),"",($A$1-H12)-365) | B12: FALSE | C12: Shree Ram Brine Chem Private Limited | D12: 6 | E12: 43963 | F12: Sonal Ghanchi | G12: Amey Joshi | H12: 45946 | I12: IVR C /Negative; INC | K12: =EDATE(H12,12) -> 46311 | L12: Ramchandran Chellam | N12: pf@pkmg.co.in | R12: Transfer | U12: IVR C /Negative; INC
A13: =IF(OR(I13="Withdrawn",R13="Transfer"),"",($A$1-H13)-365) | B13: FALSE | C13: Chintpurni Steel Private | D13: 64.7 | E13: 45318 | F13: Suresh Mandan | G13: Gurav Jain | H13: 45947 | I13: IVR BB /Negative; INC | J13: IVR A4; INC | K13: =EDATE(H13,12) -> 46312 | L13: Mr. Vikash Kumar | M13: 8340714369 | N13: cspl2005@yahoo.com | R13: Transfer | U13: IVR C- /Negative; INC
A14: =IF(OR(I14="Withdrawn",R14="Transfer"),"",($A$1-H14)-365) | B14: FALSE | C14: Narsimha Iron & Steel Private Limited | D14: 14.91 | E14: 45349 | F14: Suresh Mandan | G14: Gurav Jain | H14: 45947 | I14: IVR BB /Negative; INC | K14: =EDATE(H14,12) -> 46312 | L14: Mr. Keshav Agarwal | M14: 9199307777 | N14: narsimhairon@gmail.com | R14: Transfer | U14: IVR D; INC
A15: =IF(OR(I15="Withdrawn",R15="Transfer"),"",($A$1-H15)-365) | B15: FALSE | C15: Sri Shyam Fashion India Private Limited | F15: Dharna Bhadani | G15: Sudarshan Shreenivas | H15: 45947 | I15: IVR B+ /Negative; INC | J15: IVR A4; INC | K15: =EDATE(H15,12) -> 46312 | L15: Narendra Mallawat | N15: finance@shyamfashion.com,saurav@shyamfashion.com | R15: Transfer | U15: Withdrawn
A16: =IF(OR(I16="Withdrawn",R16="Transfer"),"",($A$1-H16)-365) | B16: FALSE | C16: PHN Technology Private Limited | D16: 99.78 | E16: 45953 | F16: Nilesh Gupta | G16: Amey Joshi | H16: 45953 | I16: IVR BB+ /Negative; INC | K16: =EDATE(H16,12) -> 46318 | N16: karn.gaikwad@phntechnology.com kiran.ghanate@phntechnology.com | R16: Transfer
A17: =IF(OR(I17="Withdrawn",R17="Transfer"),"",($A$1-H17)-365) | B17: FALSE | C17: Compuage Infocom Limited | D17: 960 | E17: 44992 | F17: Rajsee Warang | G17: Amey Joshi | H17: 45957 | I17: IVR D; INC | J17: IVR D; INC | K17: =EDATE(H17,12) -> 46322 | L17: Rency Jacob | N17: Ms. Anmol jolly <anmol.jolly@compuageindia.com> | R17: Transfer
A18: =IF(OR(I18="Withdrawn",R18="Transfer"),"",($A$1-H18)-365) | B18: FALSE | C18: Shree Biradev Finance Private Limited | D18: 37 | E18: 10/27/2025 | F18: Rajsee Warang | G18: Amey Joshi | H18: 45957 | I18: IVR BB+ /Negative; INC | K18: =EDATE(H18,12) -> 46322 | N18: Ms. Nandini Raghoji <nandiniraghoji.2192@gmail.com>; Ramachandra Raghoji <birdevfinance.fin@gmail.com | R18: Transfer
A19: =IF(OR(I19="Withdrawn",R19="Transfer"),"",($A$1-H19)-365) | B19: FALSE | C19: Indreshwar Sugar Mills Ltd | F19: Ruchika Gada | G19: Sudarshan Shreenivas | H19: 45958 | I19: IVR B- /Negative; INC | K19: =EDATE(H19,12) -> 46323 | L19: Sachin Shinde | N19: shinde.sachin9@gmail.com, isml.sugar@gmail.com | R19: Transfer
A20: =IF(OR(I20="Withdrawn",R20="Transfer"),"",($A$1-H20)-365) | B20: FALSE | C20: MEP Longjian CLR Private Limited | D20: 550.05 | E20: 44315 | F20: Shubham Hande | G20: Amey Joshi | H20: 45959 | I20: IVR C- /Negative; INC | K20: =EDATE(H20,12) -> 46324 | L20: Ashish Sharma | N20: fin@mepinfra.com sakadam@mepinfra.com | R20: Transfer
A21: =IF(OR(I21="Withdrawn",R21="Transfer"),"",($A$1-H21)-365) | B21: FALSE | C21: MEP Longjian Loha Waranga Road Private Limited | D21: 588.75 | E21: 44315 | F21: Shubham Hande | G21: Amey Joshi | H21: 45959 | I21: IVR C- /Negative; INC | K21: =EDATE(H21,12) -> 46324 | L21: Angela Sarna | N21: fin@mepinfra.com sakadam@mepinfra.com | R21: Transfer
A22: =IF(OR(I22="Withdrawn",R22="Transfer"),"",($A$1-H22)-365) | B22: FALSE | C22: MEP Longjian VTR Private Limited | D22: 646.93 | E22: 44315 | F22: Shubham Hande | G22: Amey Joshi | H22: 45959 | I22: IVR C- /Negative; INC | K22: =EDATE(H22,12) -> 46324 | L22: Mr. Naveen Kumar | M22: 9008779952 | N22: fin@mepinfra.com sakadam@mepinfra.com | R22: Transfer
A23: =IF(OR(I23="Withdrawn",R23="Transfer"),"",($A$1-H23)-365) | B23: FALSE | C23: S.V Distributors Private Limited | D23: 111 | E23: 45511 | F23: Pratik Prajapati | G23: Gurav Jain | H23: 45959 | I23: IVR D; INC | J23: IVR D; INC | K23: =EDATE(H23,12) -> 46324 | L23: Mr. Santosh Wagle | M23: 9823428798 | N23: santoshwagleicedd@gmail.com | R23: Transfer
A24: =IF(OR(I24="Withdrawn",R24="Transfer"),"",($A$1-H24)-365) | B24: FALSE | C24: Silpa Projects & Infrastructure (India) Private Limited | F24: Rahul Jadhav | G24: Sudarshan Shreenivas | H24: 45959 | I24: IVR B /Negative; INC | J24: IVR A4; INC | K24: =EDATE(H24,12) -> 46324 | L24: Mr. SASANTH SANKER -9744722039 | N24: accts@silpa.in | R24: Transfer
A25: =IF(OR(I25="Withdrawn",R25="Transfer"),"",($A$1-H25)-365) | B25: FALSE | C25: Aditya Auto Industries | D25: 19.89 | E25: 44207 | F25: Shruti P. Sagothia | G25: Amey Joshi | H25: 45960 | I25: IVR B- /Negative; INC | K25: =EDATE(H25,12) -> 46325 | L25: Mr. Milind Murudkar | M25: 9819002025 | N25: bdm@apipl.co.in | R25: Transfer
A26: =IF(OR(I26="Withdrawn",R26="Transfer"),"",($A$1-H26)-365) | B26: FALSE | C26: Sivanssh Infrastructure Development Private Limited | D26: 120 | E26: 45134 | F26: Shruti P. Sagothia | G26: Amey Joshi | H26: 45960 | I26: IVR B+ /Negative; INC | J26: IVR A4; INC | K26: =EDATE(H26,12) -> 46325 | L26: Ms. Punitha K | M26: 9677714382 | N26: neha.kamra@atsgreens.com, lovely.pathak@atsgreens.com | R26: Transfer
A27: =IF(OR(I27="Withdrawn",R27="Transfer"),"",($A$1-H27)-365) | B27: FALSE | C27: SISL Infotech | D27: 130 | E27: 44725 | F27: Sonal Ghanchi | G27: Amey Joshi | H27: 45961 | I27: IVR B+ /Negative; INC | J27: IVR A4; INC | K27: =EDATE(H27,12) -> 46326 | L27: Ms. G Sujata GM | M27: 9380528473 | N27: akash_nangia@sislinfotech.com, rohit_garg@sislinfotech.com, ranjeet_yadav@sislinfotech.com, hemant_chansoriya@sislinfotech.com> | R27: Transfer
A28: =IF(OR(I28="Withdrawn",R28="Transfer"),"",($A$1-H28)-365) | B28: FALSE | C28: SMBT Sevabhavi Trust | D28: 229.65 | E28: 45552 | F28: Kajal Chhetija | G28: Gurav Jain | H28: 45961 | I28: IVR B+ /Negative; INC | J28: IVR A4; INC | K28: =EDATE(H28,12) -> 46326 | L28: D. P. Borhade | M28: 9011067113 | N28: fintax@smbt.edu.in | R28: Transfer
A29: =IF(OR(I29="Withdrawn",R29="Transfer"),"",($A$1-H29)-365) | B29: FALSE | C29: KLSR Infratech Limited | D29: 400 | E29: 45430 | F29: Pratik | G29: Rekha Chokkalingam | H29: 45964 | I29: IVR BB /Negative; INC | J29: IVR A4; INC | K29: =EDATE(H29,12) -> 46329 | L29: K L Sreedhar Reddy | M29: 9966969669 | N29: gsr@klsrinfratech.com | R29: Transfer
A30: =IF(OR(I30="Withdrawn",R30="Transfer"),"",($A$1-H30)-365) | B30: FALSE | C30: MEP Longjian ACR Private Limited | D30: 469.77 | E30: 44315 | F30: Shubham Hande | G30: Amey Joshi | H30: 45964 | I30: IVR C- /Negative; INC | K30: =EDATE(H30,12) -> 46329 | L30: Vinay Agarwal | M30: 9646526666 | N30: fin@mepinfra.com sakadam@mepinfra.com | R30: Transfer
A31: =IF(OR(I31="Withdrawn",R31="Transfer"),"",($A$1-H31)-365) | B31: FALSE | C31: Savera Auto Comps Private Limited | F31: Palak Dand | G31: Sudarshan Shreenivas | H31: 45964 | I31: IVR BB- /Negative; INC | K31: =EDATE(H31,12) -> 46329 | N31: account@saveraengineering.com | R31: Transfer
A32: =IF(OR(I32="Withdrawn",R32="Transfer"),"",($A$1-H32)-365) | B32: FALSE | C32: Maple Logistics Pvt Ltd | D32: 100 | E32: March 27, 2019 | F32: Abhishek Nangia | G32: Gurav Jain | H32: 45965 | I32: IVR D; INC | J32: IVR D; INC | K32: =EDATE(H32,12) -> 46330 | L32: Vijay Chugh | M32: 9810332924 | N32: anil@worldswindow.cc | R32: Transfer
A33: =IF(OR(I33="Withdrawn",R33="Transfer"),"",($A$1-H33)-365) | B33: FALSE | C33: Rasik Products Private Limited | D33: 41.47 | E33: October 5, 2023 | F33: Abhishek Nangia | G33: Gurav Jain | H33: 45965 | I33: IVR D; INC | J33: IVR D; INC | K33: =EDATE(H33,12) -> 46330 | L33: Shri Girdhari Lal Khandelwal | M33: 8979388899 | N33: rasikproducts@gmail.com | R33: Transfer
A34: =IF(OR(I34="Withdrawn",R34="Transfer"),"",($A$1-H34)-365) | B34: FALSE | C34: Worlds Window Impex India Private Limited | D34: 1000 | E34: March 27, 2019 | F34: Abhishek Nangia | G34: Gurav Jain | H34: 45965 | I34: IVR D; INC | J34: IVR D; INC | K34: =EDATE(H34,12) -> 46330 | L34: Anil Mishra | M34: 9810332923 | N34: anil@worldswindow.cc | R34: Transfer
A35: =IF(OR(I35="Withdrawn",R35="Transfer"),"",($A$1-H35)-365) | B35: FALSE | C35: Global Ores & Alloy Private Limited | F35: Omkar | G35: Jyotsna | H35: 45968 | I35: IVR BB /Negative; INC | J35: IVR A4; INC | K35: =EDATE(H35,12) -> 46333 | L35: Raventh | M35: 7010804581 | N35: chairman@thebharathgroup.com | R35: Transfer
A36: =IF(OR(I36="Withdrawn",R36="Transfer"),"",($A$1-H36)-365) | B36: FALSE | C36: Posco-Poggenamp Electrical Steel Private Limited | D36: 20 | F36: Shruti P. Sagothia | G36: Amey Joshi | H36: 45968 | I36: IVR D; INC | K36: =EDATE(H36,12) -> 46333 | N36: juneja@poggenamp.com | R36: Transfer
A37: =IF(OR(I37="Withdrawn",R37="Transfer"),"",($A$1-H37)-365) | B37: FALSE | C37: Ramkrishna Cotspin Private Limited | D37: 61.23 | E37: 45968 | F37: Pratik Prajapati | G37: Gurav Jain | H37: 45968 | I37: IVR C /Negative; INC | J37: IVR A4; INC | K37: =EDATE(H37,12) -> 46333 | L37: Ramesh Piprottar | M37: 9898638450 | N37: account@rkcotspin.com | R37: Transfer
A38: =IF(OR(I38="Withdrawn",R38="Transfer"),"",($A$1-H38)-365) | B38: FALSE | C38: Jathar Spinning Private Limited | D38: 57.76 | E38: 45971 | F38: Kajal Chhetija | G38: Gurav Jain | H38: 45971 | I38: IVR BB /Negative; INC | J38: IVR A4; INC | K38: =EDATE(H38,12) -> 46336 | L38: Satish Manohar Jathar | M38: 9822260643 | N38: jathargroup@rediffmail.com | R38: Transfer
A39: =IF(OR(I39="Withdrawn",R39="Transfer"),"",($A$1-H39)-365) | B39: FALSE | C39: Bharath Hi-Tecch Builders Private Limited | F39: Omkar | G39: Jyotsna | H39: 45975 | I39: IVR BB- /Negative; INC | J39: IVR A4; INC | K39: =EDATE(H39,12) -> 46340 | L39: Raventh | M39: 7010804580 | N39: chairman@thebharathgroup.com | R39: Transfer
A40: =IF(OR(I40="Withdrawn",R40="Transfer"),"",($A$1-H40)-365) | B40: FALSE | C40: Kamala Ginning and Oil Industries Private Limited | D40: 42 | E40: 45975 | F40: Jithin | G40: Rekha Chokkalingam | H40: 45975 | I40: IVR BB- /Negative; INC | K40: =EDATE(H40,12) -> 46340 | L40: VINODKUMAR UMASANKAR SINGH | M40: 9537936809 | N40: kgoibhainsa@gmail.com | R40: Transfer
A41: =IF(OR(I41="Withdrawn",R41="Transfer"),"",($A$1-H41)-365) | B41: FALSE | C41: Kedareshwar Khandsari Udyog Private Limited | D41: 91.35 | E41: 45975 | F41: Pratik Prajapati | G41: Gurav Jain | H41: 45975 | I41: IVR BB+ /Negative; INC | J41: IVR A4+; INC | K41: =EDATE(H41,12) -> 46340 | L41: Ashishkumar Fulchand Goyal | M41: 9764134054 | N41: skkunimbhora@rediffmail.com | R41: Transfer
A42: =IF(OR(I42="Withdrawn",R42="Transfer"),"",($A$1-H42)-365) | B42: FALSE | C42: Miracle Enterprises | F42: Rahul Jadhav | G42: Sudarshan Shreenivas | H42: 45978 | I42: IVR D; INC | K42: =EDATE(H42,12) -> 46343 | L42: Jai Chotalia | N42: miracleenterprise07@gmail.com | R42: Transfer
A43: =IF(OR(I43="Withdrawn",R43="Transfer"),"",($A$1-H43)-365) | B43: FALSE | C43: Agroh Rewa Ring Road Private Limited | F43: Nikita | G43: Jyotsna | H43: 45979 | I43: IVR D; INC | K43: =EDATE(H43,12) -> 46344 | L43: Abhishek Goyal | M43: 9179018884 | N43: aidplindore@gmail.com | R43: Transfer
A44: =IF(OR(I44="Withdrawn",R44="Transfer"),"",($A$1-H44)-365) | B44: FALSE | C44: Chemtrade Overseas Private Limited | D44: 25 | E44: 43836 | F44: Rajsee Warang | G44: Amey Joshi | H44: 45981 | I44: IVR C+ /Negative; INC | J44: IVR A4+; INC | K44: =EDATE(H44,12) -> 46346 | L44: Ms. Vandana Pawar | M44: 9689747079 | N44: Tax Chemtrade <tax@chemtrade.in>; Jatin Shah <jatin@chemtrade.in> | R44: Transfer
A45: =IF(OR(I45="Withdrawn",R45="Transfer"),"",($A$1-H45)-365) | B45: FALSE | C45: R E Infra Private Limited | F45: Riya | G45: Jyotsna | H45: 45981 | I45: IVR BB- /Negative; INC | J45: IVR A4; INC | K45: =EDATE(H45,12) -> 46346 | L45: Rajesh Hamdev | M45: 9322274356 | N45: acc.reinfra@gmail.com | R45: Transfer
A46: =IF(OR(I46="Withdrawn",R46="Transfer"),"",($A$1-H46)-365) | B46: FALSE | C46: SSNR Power Pvt. Ltd. | F46: Riya | G46: Jyotsna | H46: 45981 | I46: IVR BB /Negative; INC | J46: IVR A4; INC | K46: =EDATE(H46,12) -> 46346 | L46: Mr. Samanthapudi Suryanarayana Raju | M46: 9441789000 | N46: samanthapudi_9000@yahoo.co.in | R46: Transfer
A47: =IF(OR(I47="Withdrawn",R47="Transfer"),"",($A$1-H47)-365) | B47: FALSE | C47: DMG Polypack Private Limited | D47: 20 | E47: 43649 | F47: Rajsee Warang | G47: Amey Joshi | H47: 45982 | I47: IVR C /Negative; INC | J47: IVR A4; INC | K47: =EDATE(H47,12) -> 46347 | L47: Shivakumar | M47: 8341622908 | N47: Neha Kothari <accounts@dmgpolypack.com> | R47: Transfer
A48: =IF(OR(I48="Withdrawn",R48="Transfer"),"",($A$1-H48)-365) | B48: FALSE | C48: VFS Capital Limited | D48: 1100 | E48: 10/29/2025 | F48: Milan Purohit | G48: Amey Joshi | H48: 45982 | I48: IVR D; INC | K48: =EDATE(H48,12) -> 46347 | L48: Fr. John Padipurackal | M48: 9539460076 | N48: simita@vfscapital.in | R48: Transfer
A49: =IF(OR(I49="Withdrawn",R49="Transfer"),"",($A$1-H49)-365) | B49: FALSE | C49: Fortune Chemicals Limited | D49: 50 | E49: 4/13/2019 | F49: Rajsee Warang | G49: Amey Joshi | H49: 45985 | I49: IVR C- /Negative; INC | K49: =EDATE(H49,12) -> 46350 | L49: K L Sreedhar Reddy | M49: 9966969669 | N49: accounts@fortunechem.in; Mr. Navneet <gm@fortunechem.in> | R49: Transfer
A50: =IF(OR(I50="Withdrawn",R50="Transfer"),"",($A$1-H50)-365) | B50: FALSE | C50: Amar Shakti Commerce and Industries Limited | D50: 20 | E50: 44711 | F50: Pratik Prajapati | G50: Gurav Jain | H50: 45986 | I50: IVR C- /Negative; INC | K50: =EDATE(H50,12) -> 46351 | L50: Ms. Olee Das | M50: 9101378443 | N50: oleebnc89@gmail.com | R50: Transfer
A51: =IF(OR(I51="Withdrawn",R51="Transfer"),"",($A$1-H51)-365) | B51: FALSE | C51: Shrushti Contech Private Limited | D51: 155 | E51: 45987 | F51: Shubham Hande | G51: Amey Joshi | H51: 45987 | I51: IVR BB+ /Negative; INC | J51: IVR A4+; INC | K51: =EDATE(H51,12) -> 46352 | L51: Mr. Mohit Chadda | M51: 9921545111 | N51: manikanta.ch@shrushtigroup.com raja@shrushtigroup.com madhu@shrushtigroup.com rajini.p@shrushtigroup.com maruthi.m@shrushtigroup.com | R51: Transfer
A52: =IF(OR(I52="Withdrawn",R52="Transfer"),"",($A$1-H52)-365) -> -43 | B52: FALSE | C52: MMG Holdings Private Limited | D52: 55 | F52: Dharna Bhadani | G52: Sudarshan Shreenivas | H52: 45994 | I52: IVR C+ /Negative; INC | K52: =EDATE(H52,12) -> 46359 | N52: guptaelr@gmail.com
A53: =IF(OR(I53="Withdrawn",R53="Transfer"),"",($A$1-H53)-365) -> -44 | B53: FALSE | C53: Magnifico Minerals Private Limited | D53: 400 | F53: Palak Dand | G53: Sudarshan Shreenivas | H53: 45995 | I53: IVR D; INC | J53: IVR D; INC | K53: =EDATE(H53,12) -> 46360 | N53: ashish.aggarwal@worldswindow.com
A54: =IF(OR(I54="Withdrawn",R54="Transfer"),"",($A$1-H54)-365) -> -44 | B54: FALSE | C54: Sattva Engineering Construction Pvt Ltd | D54: 69.12 | E54: 45607 | F54: Sruthi | G54: Rekha Chokkalingam | H54: 45995 | I54: IVR B /Negative; INC | J54: IVR A4; INC | K54: =EDATE(H54,12) -> 46360 | L54: Mr. Sunil Shinde | M54: 9822024345 | N54: sujatha@sattvaengg.in
A55: =IF(OR(I55="Withdrawn",R55="Transfer"),"",($A$1-H55)-365) -> -50 | B55: FALSE | C55: Castor Girnar Industries Private Limited | D55: 64 | E55: 45840 | F55: Shruti P. Sagothia | G55: Amey Joshi | H55: 46001 | I55: IVR BB+ /Negative; INC | J55: IVR A4+; INC | K55: =EDATE(H55,12) -> 46366 | L55: Shyam Prasad | M55: 9849015839 | N55: akash_nangia@sislinfotech.com, rohit_garg@sislinfotech.com, ranjeet_yadav@sislinfotech.com, hemant_chansoriya@sislinfotech.com>
A56: =IF(OR(I56="Withdrawn",R56="Transfer"),"",($A$1-H56)-365) -> -50 | B56: FALSE | C56: Jai Hind Sugar private Limited | D56: 207.25 | F56: Rahul Jadhav | G56: Sudarshan Shreenivas | H56: 46001 | I56: IVR BB+ /Negative; INC | K56: =EDATE(H56,12) -> 46366 | L56: Ms. Nikita Wakchaure-7020494378 | N56: jaihindsugar@gmail.com
A57: =IF(OR(I57="Withdrawn",R57="Transfer"),"",($A$1-H57)-365) -> -51 | B57: FALSE | C57: Jaywant Sugars Limited | D57: 524.36 | F57: Pratik Prabhu | G57: Sudarshan Shreenivas | H57: 46002 | I57: IVR BB- /Negative; INC | K57: =EDATE(H57,12) -> 46367 | L57: Vijaykumar Savarikar - 9011592154 | N57: account@jaywantsugars.com, cfojaywantsugars@gmail.com
A58: =IF(OR(I58="Withdrawn",R58="Transfer"),"",($A$1-H58)-365) -> -52 | B58: FALSE | C58: Agroh Kodinar Veraval Highways Private limited | D58: 100 | F58: Nikita | G58: Jyotsna | H58: 46003 | I58: IVR B+ /Negative; INC | K58: =EDATE(H58,12) -> 46368 | L58: Abhishek Goyal | M58: 9179018884 | N58: aidplindore@gmail.com
A59: =IF(OR(I59="Withdrawn",R59="Transfer"),"",($A$1-H59)-365) -> -52 | B59: FALSE | C59: Chrysalis Trading Private Limited | D59: 15 | F59: Srushti Patil | G59: Sudarshan Shreenivas | H59: 46003 | I59: IVR D; INC | K59: =EDATE(H59,12) -> 46368 | L59: Mr.Virender Rawat-9560273021 | N59: financechrysalis5@gmail.com
A60: =IF(OR(I60="Withdrawn",R60="Transfer"),"",($A$1-H60)-365) -> -56 | B60: FALSE | C60: Caliber Mercantile Private Limited | D60: 348.41 | E60: 45381 | F60: Pratik | G60: Rekha Chokkalingam | H60: 46007 | I60: IVR BB /Negative; INC | J60: IVR A4; INC | K60: =EDATE(H60,12) -> 46372 | L60: Mr. Mohit Chadda | M60: 9921545111 | N60: sachin.t@cmll.in
A61: =IF(OR(I61="Withdrawn",R61="Transfer"),"",($A$1-H61)-365) -> -58 | B61: FALSE | C61: IIT-ians Pace Education Private Limited | D61: 33.94 | E61: 45615 | F61: Pratik Prajapati | G61: Gurav Jain | H61: 46009 | I61: IVR B+ /Negative; INC | K61: =EDATE(H61,12) -> 46374 | L61: Supriti Sabat | M61: 9136113791 | N61: accounts@iitanspace.com
A62: =IF(OR(I62="Withdrawn",R62="Transfer"),"",($A$1-H62)-365) -> -58 | B62: FALSE | C62: Radharaman Cotspin Private Limited | D62: 68.75 | E62: 45615 | F62: Kajal Chhetija | G62: Gurav Jain | H62: 46009 | I62: IVR B- /Negative; INC | J62: IVR A4; INC | K62: =EDATE(H62,12) -> 46374 | L62: Mr Jatin P Patel | M62: 9979986986 | N62: jatinpatel434@gmail.com
A63: =IF(OR(I63="Withdrawn",R63="Transfer"),"",($A$1-H63)-365) -> -59 | B63: FALSE | C63: Best Blue Metals | D63: 20 | F63: Aniket | G63: Jyotsna | H63: 46010 | I63: IVR C+ /Negative; INC | K63: =EDATE(H63,12) -> 46375 | L63: Manoj Prabhakar | M63: 9688628888 | N63: bestbluemetals@gmail.com
A64: =IF(OR(I64="Withdrawn",R64="Transfer"),"",($A$1-H64)-365) -> -59 | B64: FALSE | C64: Sun N Wind Infra Energy Private Limited | D64: 37 | F64: Riya | G64: Jyotsna | H64: 46010 | I64: IVR B- /Negative; INC | K64: =EDATE(H64,12) -> 46375 | L64: Anuj Agrawal | M64: 9837899918 | N64: sunnwindinfra@gmail.com
A65: =IF(OR(I65="Withdrawn",R65="Transfer"),"",($A$1-H65)-365) -> -62 | B65: FALSE | C65: Tirumala Tirupati Rice Mill Private Limited | D65: 14 | E65: 44833 | F65: Suresh Mandan | G65: Gurav Jain | H65: 46013 | I65: IVR C+ /Negative; INC | J65: IVR A4; INC | K65: =EDATE(H65,12) -> 46378 | L65: Ms. Sushmita Nayak | M65: 9437085017 | N65: tirumalatirupatiricemill.ada@gmail.com
A66: =IF(OR(I66="Withdrawn",R66="Transfer"),"",($A$1-H66)-365) -> -63 | B66: FALSE | C66: Jai Hind Feeds | D66: 25.3 | E66: 45611 | F66: Rahul Saini | G66: Gurav Jain | H66: 46014 | I66: IVR BB- /Negative; INC | J66: IVR A4; INC | K66: =EDATE(H66,12) -> 46379 | L66: Maya Jamdar | M66: 9420343003 | N66: jaihindfeeds@gmail.com
A67: =IF(OR(I67="Withdrawn",R67="Transfer"),"",($A$1-H67)-365) -> -64 | B67: FALSE | C67: Anoj Kumar Agarwala | F67: Ruchika Gada | G67: Sudarshan Shreenivas | H67: 46015 | I67: IVR B+ /Negative; INC | J67: IVR A4; INC | K67: =EDATE(H67,12) -> 46380 | L67: Anoj Agarwala | N67: anojagarwala@rediffmail.com
A68: =IF(OR(I68="Withdrawn",R68="Transfer"),"",($A$1-H68)-365) -> -64 | B68: FALSE | C68: Prince Corp Private Limited | F68: Pratik Prabhu | G68: Sudarshan Shreenivas | H68: 46015 | I68: IVR D; INC | J68: IVR D; INC | K68: =EDATE(H68,12) -> 46380 | L68: Rakesh Chadda - 9820212120, Jagdish Nathani- 9167 128362 | N68: raakesh@princeware.net, jagdishnathani@princeware.net
A69: =IF(OR(I69="Withdrawn",R69="Transfer"),"",($A$1-H69)-365) -> -64 | B69: FALSE | C69: Quality Exports | F69: Ruchika Gada | G69: Sudarshan Shreenivas | H69: 46015 | I69: IVR B+ /Negative; INC | J69: IVR A4; INC | K69: =EDATE(H69,12) -> 46380 | L69: Arun Naik | N69: qualityexportsgoa@gmail.com
A70: =IF(OR(I70="Withdrawn",R70="Transfer"),"",($A$1-H70)-365) -> -69 | B70: FALSE | C70: IRP Infra Tech Private Limited | F70: Palak Dand | G70: Sudarshan Shreenivas | H70: 46020 | I70: IVR BB- /Negative; INC | J70: IVR A4; INC | K70: =EDATE(H70,12) -> 46385 | N70: irpinfratech@yahoo.in
A71: =IF(OR(I71="Withdrawn",R71="Transfer"),"",($A$1-H71)-365) -> -69 | B71: FALSE | C71: Sarna Chemicals Private Limited | D71: 20 | E71: 45845 | F71: Rahul Saini | G71: Gurav Jain | H71: 46020 | I71: IVR BB+ /Negative; INC | J71: IVR A4+; INC | K71: =EDATE(H71,12) -> 46385 | L71: Jitendra Prajapat | M71: 9909991872 | N71: ac1@sarnachemicals.com
A72: =IF(OR(I72="Withdrawn",R72="Transfer"),"",($A$1-H72)-365) -> -69 | B72: FALSE | C72: Shriniwas Spintex Industries Pvt Ltd | F72: Palak Dand | G72: Sudarshan Shreenivas | H72: 46020 | I72: IVR BB /Negative; INC | J72: IVR A4; INC | K72: =EDATE(H72,12) -> 46385 | N72: shriniwasspintex@gmail.com
A73: =IF(OR(I73="Withdrawn",R73="Transfer"),"",($A$1-H73)-365) -> -69 | B73: FALSE | C73: Tirumalla Groundnuts Industries India Private Limited | F73: Palak Dand | G73: Sudarshan Shreenivas | H73: 46020 | I73: IVR D; INC | K73: =EDATE(H73,12) -> 46385 | N73: headoffice@thekutegroup.com
A74: =IF(OR(I74="Withdrawn",R74="Transfer"),"",($A$1-H74)-365) -> -69 | B74: FALSE | C74: Tirumalla Oil Refinery Private Limited | F74: Palak Dand | G74: Sudarshan Shreenivas | H74: 46020 | I74: IVR D; INC | K74: =EDATE(H74,12) -> 46385 | N74: headoffice@thekutegroup.com
A75: =IF(OR(I75="Withdrawn",R75="Transfer"),"",($A$1-H75)-365) -> -71 | B75: FALSE | C75: Madhya Pradesh Power Generating Company Limited | F75: Anupriya | G75: Jyotsna | H75: 46022 | I75: IVR B+ /Negative; INC | K75: =EDATE(H75,12) -> 46387 | L75: Ms. Reshmi Pal | M75: 9926659276 | N75: cashmppgcl@gmail.com
A76: =IF(OR(I76="Withdrawn",R76="Transfer"),"",($A$1-H76)-365) -> -72 | B76: FALSE | C76: Worlds Window Infra & Logistics Pvt Ltd | D76: 130 | E76: March 28, 2019 | F76: Abhishek Nangia | G76: Gurav Jain | H76: 46023 | I76: IVR D; INC | J76: IVR D; INC | K76: =EDATE(H76,12) -> 46388 | L76: Anil Mishra | M76: 9810332923 | N76: anil@worldswindow.cc
A77: =IF(OR(I77="Withdrawn",R77="Transfer"),"",($A$1-H77)-365) -> -73 | B77: FALSE | C77: Melzer Chemicals Private Limited | D77: 57.04 | E77: 45197 | F77: Pratik | G77: Rekha Chokkalingam | H77: 46024 | I77: IVR BB- /Negative; INC | J77: IVR A4; INC | K77: =EDATE(H77,12) -> 46389 | L77: Mr. Sunil Shinde | M77: 9822024345 | N77: accounts@melzerspeciality.com
A78: =IF(OR(I78="Withdrawn",R78="Transfer"),"",($A$1-H78)-365) -> -79 | B78: FALSE | C78: R C Apparels | F78: Srushti Patil | G78: Sudarshan Shreenivas | H78: 46030 | I78: IVR BB /Negative; INC | J78: IVR A4; INC | K78: =EDATE(H78,12) -> 46395 | L78: Abhishek Jain-9911181120 | N78: abhishekjain@rcapparels.com
A79: =IF(OR(I79="Withdrawn",R79="Transfer"),"",($A$1-H79)-365) -> -83 | B79: FALSE | C79: Dhansamridhi Finance Private Limited | D79: 150 | E79: 46357 | F79: Milan Purohit | G79: Amey Joshi | H79: 46034 | I79: IVR BB+ /Negative; INC | K79: =EDATE(H79,12) -> 46399 | M79: 7624998984 | N79: goelnakul@gmail.com, accounts@dhansamridhi.com
A80: =IF(OR(I80="Withdrawn",R80="Transfer"),"",($A$1-H80)-365) -> -83 | B80: FALSE | C80: Kute Sons Dairys Limited | D80: 269.17 | E80: 45299 | F80: Nilesh Gupta | G80: Amey Joshi | H80: 46034 | I80: IVR D; INC | K80: =EDATE(H80,12) -> 46399 | N80: headoffice@thekutegroup.com sachin.patni@tirumallaoil.com ashishptdkr@gmail.com
A81: =IF(OR(I81="Withdrawn",R81="Transfer"),"",($A$1-H81)-365) -> -83 | B81: FALSE | C81: Kute Sons Fresh Dairy Private Limited | D81: 44.9 | E81: 45299 | F81: Nilesh Gupta | G81: Amey Joshi | H81: 46034 | I81: IVR D; INC | K81: =EDATE(H81,12) -> 46399 | N81: headoffice@thekutegroup.com sachin.patni@tirumallaoil.com ashishptdkr@gmail.com
A82: =IF(OR(I82="Withdrawn",R82="Transfer"),"",($A$1-H82)-365) -> -84 | B82: FALSE | C82: KHFM Hospitality and Facility Management Services Limited | D82: 64.23 | E82: 45220 | F82: Nilesh Gupta | G82: Amey Joshi | H82: 46035 | I82: IVR D; INC | K82: =EDATE(H82,12) -> 46400 | N82: cs@khfm.in
A83: =IF(OR(I83="Withdrawn",R83="Transfer"),"",($A$1-H83)-365) -> -90 | B83: FALSE | C83: Harsha International | D83: 28.08 | F83: Jithin | G83: Rekha Chokkalingam | H83: 46041 | I83: IVR D; INC | K83: =EDATE(H83,12) -> 46406 | L83: B Maharudrappa | M83: 7337639566 | N83: harshabm2@gmail.com
A84: =IF(OR(I84="Withdrawn",R84="Transfer"),"",($A$1-H84)-365) -> -94 | B84: FALSE | C84: IQRA Microfinance Federation | D84: 3 | E84: 45170 | F84: Milan Purohit | G84: Amey Joshi | H84: 46045 | I84: IVR C+ /Negative; INC | K84: =EDATE(H84,12) -> 46410 | L84: Vuppala .Harsha Vardhan Reddy | M84: 9652828883 | N84: iqramicrofinancefederation@gmail.com
A85: =IF(OR(I85="Withdrawn",R85="Transfer"),"",($A$1-H85)-365) -> -94 | B85: FALSE | C85: Mundhe Industries Pvt Ltd | D85: 84.91 | F85: Rajsee Warang | G85: Amey Joshi | H85: 46045 | I85: IVR BB- /Negative; INC | K85: =EDATE(H85,12) -> 46410 | M85: 9552647944 | N85: mundhesuyesh955@gmail.com
A86: =IF(OR(I86="Withdrawn",R86="Transfer"),"",($A$1-H86)-365) -> -94 | B86: FALSE | C86: Swadha Finlease Private Limited | D86: 3 | E86: 45170 | F86: Milan Purohit | G86: Amey Joshi | H86: 46045 | I86: IVR B- /Negative; INC | K86: =EDATE(H86,12) -> 46410 | L86: CS Nadeem | M86: 7879533688 | N86: swadhafinlease@gmail.com
A87: =IF(OR(I87="Withdrawn",R87="Transfer"),"",($A$1-H87)-365) -> -99 | B87: FALSE | C87: Eagle Steels Rolling Mill | F87: Dharna Bhadani | G87: Sudarshan Shreenivas | H87: 46050 | I87: IVR D; INC | J87: IVR D; INC | K87: =EDATE(H87,12) -> 46415 | L87: Amrit Lal Shah | N87: eagleamritlal@yahoo.in,info@eaglesteels.com
A88: =IF(OR(I88="Withdrawn",R88="Transfer"),"",($A$1-H88)-365) -> -99 | B88: FALSE | C88: Seagull Maritime Agencies Private Limited | F88: Dharna Bhadani | G88: Sudarshan Shreenivas | H88: 46050 | I88: IVR D; INC | K88: =EDATE(H88,12) -> 46415 | N88: pawan@seagull-global.com
A89: =IF(OR(I89="Withdrawn",R89="Transfer"),"",($A$1-H89)-365) -> -99 | B89: FALSE | C89: Viyan Tex Industries LLP | F89: Pratik Prabhu | G89: Sudarshan Shreenivas | H89: 46050 | I89: IVR BB /Negative; INC | J89: IVR A4; INC | K89: =EDATE(H89,12) -> 46415 | L89: Mr. Shrinivas - 9850308030 | N89: shriniwasspintex@gmail.com
A90: =IF(OR(I90="Withdrawn",R90="Transfer"),"",($A$1-H90)-365) -> -100 | B90: FALSE | C90: Heera Ind Trading Private Limited | D90: 40 | E90: 44803 | F90: Nilesh Gupta | G90: Amey Joshi | H90: 46051 | I90: IVR D; INC | K90: =EDATE(H90,12) -> 46416 | N90: ravi@heerabgroup.com
A91: =IF(OR(I91="Withdrawn",R91="Transfer"),"",($A$1-H91)-365) -> -100 | B91: FALSE | C91: Pratham Heera Sales Private Limited | D91: 45 | E91: 44803 | F91: Nilesh Gupta | G91: Amey Joshi | H91: 46051 | I91: IVR D; INC | K91: =EDATE(H91,12) -> 46416 | N91: ravi@heerabgroup.com
A92: =IF(OR(I92="Withdrawn",R92="Transfer"),"",($A$1-H92)-365) -> -106 | B92: FALSE | C92: Annai Resorts and Spa Private Limited | D92: 8.73 | E92: 45643 | F92: Pratik | G92: Rekha Chokkalingam | H92: 46057 | I92: IVR B+ /Negative; INC | K92: =EDATE(H92,12) -> 46422 | L92: S. Gnanathiraviam | M92: 9123575701 | N92: annairesorts@gmail.com
A93: =IF(OR(I93="Withdrawn",R93="Transfer"),"",($A$1-H93)-365) -> -106 | B93: FALSE | C93: ETO Motors Private Limited | D93: 50 | E93: 45209 | F93: Pratik | G93: Rekha Chokkalingam | H93: 46057 | I93: IVR B- /Negative; INC | K93: =EDATE(H93,12) -> 46422 | L93: Shyam Prasad | M93: 9849015839 | N93: satyam@etomotors.com
A94: =IF(OR(I94="Withdrawn",R94="Transfer"),"",($A$1-H94)-365) -> -107 | B94: FALSE | C94: Vamica Resorts Pvt Ltd | F94: Nikita | G94: Jyotsna | H94: 46058 | I94: IVR B /Negative; INC | K94: =EDATE(H94,12) -> 46423 | L94: Jitendra Verma | M94: 7803800004 | N94: jatin@vamicaresorts.com;vamicaresort003@gmail.com
A95: =IF(OR(I95="Withdrawn",R95="Transfer"),"",($A$1-H95)-365) -> -108 | B95: FALSE | C95: Shri Mahesh Co-operative Spinning Mills Limited | F95: Aniket | G95: Jyotsna | H95: 46059 | I95: IVR B+ /Negative; INC | J95: IVR A4; INC | K95: =EDATE(H95,12) -> 46424 | L95: Amol Palkar | M95: 8888301140 | N95: shreemahesh.spin@yahoo.in
A96: =IF(OR(I96="Withdrawn",R96="Transfer"),"",($A$1-H96)-365) -> -111 | B96: FALSE | C96: Enzotech Solutions | F96: Dharna Bhadani | G96: Sudarshan Shreenivas | H96: 46062 | I96: IVR C+ /Negative; INC | J96: IVR A4; INC | K96: =EDATE(H96,12) -> 46427 | N96: finance@enzotech.co.in
A97: =IF(OR(I97="Withdrawn",R97="Transfer"),"",($A$1-H97)-365) -> -111 | B97: FALSE | C97: Radiant Industries | F97: Dharna Bhadani | G97: Sudarshan Shreenivas | H97: 46062 | I97: IVR C+ /Negative; INC | J97: IVR A4; INC | K97: =EDATE(H97,12) -> 46427 | L97: Arun | N97: arun@radiantindia.net
A98: =IF(OR(I98="Withdrawn",R98="Transfer"),"",($A$1-H98)-365) -> -112 | B98: FALSE | C98: Shree Manglam Buildcon (I) Private Limited | D98: 121 | E98: 45644 | F98: Pratik Prajapati | G98: Gurav Jain | H98: 46063 | I98: IVR BB /Negative; INC | J98: IVR A4; INC | K98: =EDATE(H98,12) -> 46428 | L98: Mangesh Annachhatre | M98: 9371642430 | N98: mangesha@womindia.com
A99: =IF(OR(I99="Withdrawn",R99="Transfer"),"",($A$1-H99)-365) -> -112 | B99: FALSE | C99: Vimla Fuels & Metals Limited | F99: Riya | G99: Jyotsna | H99: 46063 | I99: IVR D; INC | J99: IVR D; INC | K99: =EDATE(H99,12) -> 46428 | L99: Hitesh Joshi | M99: 9586792404 | N99: accvfmpl@gmail.com
A100: =IF(OR(I100="Withdrawn",R100="Transfer"),"",($A$1-H100)-365) -> -114 | B100: FALSE | C100: Sunstream City Private Limited | D100: 817.9 | F100: Nilesh Gupta | G100: Amey Joshi | H100: 46065 | I100: IVR D; INC | K100: =EDATE(H100,12) -> 46430
...

Sheet Sheet2
C1: 46265 | D1: 46266 | E1: 46267 | F1: 46268 | G1: 46272 | H1: 46273 | I1: 46287 | J1: 46295 | K1: 46297 | L1: 46307
C2: 46265 | D2: 46266 | E2: 46267 | F2: 46268 | G2: 46272 | H2: 46273 | I2: =I1 -> 46287 | J2: =J1 -> 46295 | K2: =K1 -> 46297 | L2: =L1 -> 46307
B3: Parin Gems | C3: TRUE | D3: TRUE | E3: TRUE | F3: TRUE | G3: TRUE | H3: TRUE
B4: Prakruti Products Private Limited | C4: TRUE | D4: TRUE | E4: TRUE | F4: TRUE | G4: TRUE | H4: TRUE
B5: Furniture Points | C5: TRUE | D5: TRUE | E5: TRUE | F5: TRUE | G5: TRUE | H5: TRUE
B6: Shree Ram Resins Private Limited | C6: TRUE | D6: TRUE | E6: TRUE | F6: TRUE | G6: TRUE | H6: TRUE
B7: Shri Nagal Aluminium Company | C7: TRUE | D7: TRUE | E7: TRUE | F7: TRUE | G7: TRUE | H7: TRUE
B8: Creaative Powertech Private Limited | C8: TRUE | D8: TRUE | E8: TRUE | F8: TRUE | G8: TRUE | H8: TRUE
B9: Share India Securities Limited | C9: TRUE | D9: TRUE | E9: TRUE | F9: TRUE | G9: TRUE | H9: TRUE
B10: Apollo Green Energy Limited | C10: TRUE | D10: TRUE | E10: TRUE | F10: TRUE | G10: TRUE | H10: TRUE
B11: Sustainable Agro-Commercial Finance Limited | C11: TRUE | D11: TRUE | E11: TRUE | F11: TRUE | G11: TRUE | H11: TRUE
B12: Prashanth Poultry Private Limited | C12: TRUE | D12: TRUE | E12: TRUE | F12: TRUE | G12: TRUE | H12: TRUE
B13: Enn Enn Corp Limited | C13: TRUE | D13: TRUE | E13: TRUE | F13: TRUE | G13: TRUE | H13: TRUE
B14: Pushpagiri Medical Society | C14: TRUE | D14: TRUE | E14: TRUE | F14: TRUE | G14: TRUE | H14: TRUE
... B19: Swiss Garnier Genexiaa Sciences Private Limited | C19: TRUE | D19: TRUE | E19: TRUE | F19: TRUE | G19: TRUE | H19: TRUE
B20: Tristar Lifesciences Private Limited | G20: TRUE | H20: TRUE | I20: TRUE
B21: Zandros Granitos LLP | G21: TRUE | H21: TRUE | I21: TRUE
B22: Jagruti Sugar and Allied Industries Ltd | G22: TRUE | H22: TRUE | I22: TRUE
B23: Uralungal Labour Contract Co-operative Society Limited | G23: TRUE | H23: TRUE | I23: TRUE
B24: IQF Food Pvt Ltd | G24: TRUE | H24: TRUE | I24: TRUE
B25: NISA Industrial Service Private Limited | G25: TRUE | H25: TRUE | I25: TRUE
B26: Melt-O-Therm Furnaces Private | G26: TRUE | H26: TRUE | I26: TRUE
B27: Om Shri Shubh Labh Agritech Private Limited | G27: TRUE | H27: TRUE | I27: TRUE
B28: Harman Finochem Limited | G28: TRUE | H28: TRUE | I28: TRUE
B29: Acute retail Infra Private Limited | G29: TRUE | H29: TRUE | J29: TRUE
B30: Advanced Computers & Mobiles India Private Limited | G30: TRUE | H30: TRUE | J30: TRUE
B31: Grand Canyon SEZ Private Limited | J31: TRUE | K31: TRUE | L31: TRUE
B32: Aisshpra Life Spaces | J32: TRUE | K32: TRUE | L32: TRUE
B33: M/S Idupulapadu Cotton Mills Private Limited | J33: TRUE | K33: TRUE | L33: TRUE
B34: Raghava Constructions India Private Limited | J34: TRUE | K34: TRUE | L34: TRUE
B35: Renuka Realtors | J35: TRUE | K35: TRUE | L35: TRUE
B36: Aventura Components Private Limited | J36: TRUE | K36: TRUE | L36: TRUE
B41: Company name | C41: Dates
B42: Harman Finochem Limited | C42: September 07, 2026, September 08, 2026 and September 22, 2026
B43: Acute Retail Infra Private Limited | C43: September 07, 2026, September 08, 2026 and September 30, 2026
B44: Advanced Computers & Mobiles India Private Limited | C44: September 07, 2026, September 08, 2026 and September 30, 2026
B45: Grand Canyon SEZ Private Limited | C45: September 30, 2026, October 02, 2026 and October 12, 2026
B46: Aisshpra Life Spaces | C46: September 30, 2026, October 02, 2026 and October 12, 2026
B47: M/S Idupulapadu Cotton Mills Private Limited | C47: September 30, 2026, October 02, 2026 and October 12, 2026
B48: Raghava Constructions India Private Limited | C48: September 30, 2026, October 02, 2026 and October 12, 2026
B49: Renuka Realtors | C49: September 30, 2026, October 02, 2026 and October 12, 2026
B50: Aventura Components Private Limited | C50: September 30, 2026, October 02, 2026 and October 12, 2026

Sheet NCD
A1: =TODAY() -> 46316 | B1: Done | C1: Name | D1: Amount | E1: Previous Analyst | F1: Group Head | G1: Last PR date | H1: LT Rating | I1: ST Rating | J1: Next PR Date | K1: Contact Person | L1: Number | M1: Email
A2: =IF(_xlfn.XLOOKUP($C2,ALL!$C$2:$C$341,ALL!A$2:A$341)<>"",_xlfn.XLOOKUP($C2,ALL!$C$2:$C$341,ALL!A$2:A$341),"") -> Live | B2: =IF(_xlfn.XLOOKUP($C2,ALL!$C$2:$C$341,ALL!B$2:B$341)<>"",_xlfn.XLOOKUP($C2,ALL!$C$2:$C$341,ALL!B$2:B$341),"") -> FALSE | C2: India Home Loan Limited | D2: =IF(_xlfn.XLOOKUP($C2,ALL!$C$2:$C$341,ALL!D$2:D$341)<>"",_xlfn.XLOOKUP($C2,ALL!$C$2:$C$341,ALL!D$2:D$341),"") -> 54.22 | E2: =IF(_xlfn.XLOOKUP($C2,ALL!$C$2:$C$341,ALL!F$2:F$341)<>"",_xlfn.XLOOKUP($C2,ALL!$C$2:$C$341,ALL!F$2:F$341),"") -> Milan Purohit | F2: =IF(_xlfn.XLOOKUP($C2,ALL!$C$2:$C$341,ALL!G$2:G$341)<>"",_xlfn.XLOOKUP($C2,ALL!$C$2:$C$341,ALL!G$2:G$341),"") -> Amey Joshi | G2: =IF(_xlfn.XLOOKUP($C2,ALL!$C$2:$C$341,ALL!H$2:H$341)<>"",_xlfn.XLOOKUP($C2,ALL!$C$2:$C$341,ALL!H$2:H$341),"") -> 46045 | H2: =IF(_xlfn.XLOOKUP($C2,ALL!$C$2:$C$341,ALL!I$2:I$341)<>"",_xlfn.XLOOKUP($C2,ALL!$C$2:$C$341,ALL!I$2:I$341),"") -> IVR D | I2: =IF(_xlfn.XLOOKUP($C2,ALL!$C$2:$C$341,ALL!J$2:J$341)<>"",_xlfn.XLOOKUP($C2,ALL!$C$2:$C$341,ALL!J$2:J$341),"") | J2: =IF(_xlfn.XLOOKUP($C2,ALL!$C$2:$C$341,ALL!K$2:K$341)<>"",_xlfn.XLOOKUP($C2,ALL!$C$2:$C$341,ALL!K$2:K$341),"") -> 46410 | K2: =IF(_xlfn.XLOOKUP($C2,ALL!$C$2:$C$341,ALL!L$2:L$341)<>"",_xlfn.XLOOKUP($C2,ALL!$C$2:$C$341,ALL!L$2:L$341),"") -> Mr Venkateswaran | L2: =IF(_xlfn.XLOOKUP($C2,ALL!$C$2:$C$341,ALL!M$2:M$341)<>"",_xlfn.XLOOKUP($C2,ALL!$C$2:$C$341,ALL!M$2:M$341),"") -> 9750946966 | ... N2: =IF(_xlfn.XLOOKUP($C2,ALL!$C$2:$C$341,ALL!O$2:O$341)<>"",_xlfn.XLOOKUP($C2,ALL!$C$2:$C$341,ALL!O$2:O$341),"")
A3: =IF(_xlfn.XLOOKUP($C3,ALL!$C$2:$C$341,ALL!A$2:A$341)<>"",_xlfn.XLOOKUP($C3,ALL!$C$2:$C$341,ALL!A$2:A$341),"") -> -107 | B3: =IF(_xlfn.XLOOKUP($C3,ALL!$C$2:$C$341,ALL!B$2:B$341)<>"",_xlfn.XLOOKUP($C3,ALL!$C$2:$C$341,ALL!B$2:B$341),"") -> FALSE | C3: Vamica Resorts Pvt Ltd | D3: =IF(_xlfn.XLOOKUP($C3,ALL!$C$2:$C$341,ALL!D$2:D$341)<>"",_xlfn.XLOOKUP($C3,ALL!$C$2:$C$341,ALL!D$2:D$341),"") | E3: =IF(_xlfn.XLOOKUP($C3,ALL!$C$2:$C$341,ALL!F$2:F$341)<>"",_xlfn.XLOOKUP($C3,ALL!$C$2:$C$341,ALL!F$2:F$341),"") -> Nikita | F3: =IF(_xlfn.XLOOKUP($C3,ALL!$C$2:$C$341,ALL!G$2:G$341)<>"",_xlfn.XLOOKUP($C3,ALL!$C$2:$C$341,ALL!G$2:G$341),"") -> Jyotsna | G3: =IF(_xlfn.XLOOKUP($C3,ALL!$C$2:$C$341,ALL!H$2:H$341)<>"",_xlfn.XLOOKUP($C3,ALL!$C$2:$C$341,ALL!H$2:H$341),"") -> 46058 | H3: =IF(_xlfn.XLOOKUP($C3,ALL!$C$2:$C$341,ALL!I$2:I$341)<>"",_xlfn.XLOOKUP($C3,ALL!$C$2:$C$341,ALL!I$2:I$341),"") -> IVR B /Negative; INC | I3: =IF(_xlfn.XLOOKUP($C3,ALL!$C$2:$C$341,ALL!J$2:J$341)<>"",_xlfn.XLOOKUP($C3,ALL!$C$2:$C$341,ALL!J$2:J$341),"") | J3: =IF(_xlfn.XLOOKUP($C3,ALL!$C$2:$C$341,ALL!K$2:K$341)<>"",_xlfn.XLOOKUP($C3,ALL!$C$2:$C$341,ALL!K$2:K$341),"") -> 46423 | K3: =IF(_xlfn.XLOOKUP($C3,ALL!$C$2:$C$341,ALL!L$2:L$341)<>"",_xlfn.XLOOKUP($C3,ALL!$C$2:$C$341,ALL!L$2:L$341),"") -> Jitendra Verma | L3: =IF(_xlfn.XLOOKUP($C3,ALL!$C$2:$C$341,ALL!M$2:M$341)<>"",_xlfn.XLOOKUP($C3,ALL!$C$2:$C$341,ALL!M$2:M$341),"") -> 7803800004 | ... N3: =IF(_xlfn.XLOOKUP($C3,ALL!$C$2:$C$341,ALL!O$2:O$341)<>"",_xlfn.XLOOKUP($C3,ALL!$C$2:$C$341,ALL!O$2:O$341),"")
A4: =IF(_xlfn.XLOOKUP($C4,ALL!$C$2:$C$341,ALL!A$2:A$341)<>"",_xlfn.XLOOKUP($C4,ALL!$C$2:$C$341,ALL!A$2:A$341),"") -> -114 | B4: =IF(_xlfn.XLOOKUP($C4,ALL!$C$2:$C$341,ALL!B$2:B$341)<>"",_xlfn.XLOOKUP($C4,ALL!$C$2:$C$341,ALL!B$2:B$341),"") -> FALSE | C4: Sunstream City Private Limited | D4: =IF(_xlfn.XLOOKUP($C4,ALL!$C$2:$C$341,ALL!D$2:D$341)<>"",_xlfn.XLOOKUP($C4,ALL!$C$2:$C$341,ALL!D$2:D$341),"") -> 817.9 | E4: =IF(_xlfn.XLOOKUP($C4,ALL!$C$2:$C$341,ALL!F$2:F$341)<>"",_xlfn.XLOOKUP($C4,ALL!$C$2:$C$341,ALL!F$2:F$341),"") -> Nilesh Gupta | F4: =IF(_xlfn.XLOOKUP($C4,ALL!$C$2:$C$341,ALL!G$2:G$341)<>"",_xlfn.XLOOKUP($C4,ALL!$C$2:$C$341,ALL!G$2:G$341),"") -> Amey Joshi | G4: =IF(_xlfn.XLOOKUP($C4,ALL!$C$2:$C$341,ALL!H$2:H$341)<>"",_xlfn.XLOOKUP($C4,ALL!$C$2:$C$341,ALL!H$2:H$341),"") -> 46065 | H4: =IF(_xlfn.XLOOKUP($C4,ALL!$C$2:$C$341,ALL!I$2:I$341)<>"",_xlfn.XLOOKUP($C4,ALL!$C$2:$C$341,ALL!I$2:I$341),"") -> IVR D; INC | I4: =IF(_xlfn.XLOOKUP($C4,ALL!$C$2:$C$341,ALL!J$2:J$341)<>"",_xlfn.XLOOKUP($C4,ALL!$C$2:$C$341,ALL!J$2:J$341),"") | J4: =IF(_xlfn.XLOOKUP($C4,ALL!$C$2:$C$341,ALL!K$2:K$341)<>"",_xlfn.XLOOKUP($C4,ALL!$C$2:$C$341,ALL!K$2:K$341),"") -> 46430 | K4: =IF(_xlfn.XLOOKUP($C4,ALL!$C$2:$C$341,ALL!L$2:L$341)<>"",_xlfn.XLOOKUP($C4,ALL!$C$2:$C$341,ALL!L$2:L$341),"") | L4: =IF(_xlfn.XLOOKUP($C4,ALL!$C$2:$C$341,ALL!M$2:M$341)<>"",_xlfn.XLOOKUP($C4,ALL!$C$2:$C$341,ALL!M$2:M$341),"") | M4: =IF(_xlfn.XLOOKUP($C4,ALL!$C$2:$C$341,ALL!N$2:N$341)<>"",_xlfn.XLOOKUP($C4,ALL!$C$2:$C$341,ALL!N$2:N$341),"")
A5: =IF(_xlfn.XLOOKUP($C5,ALL!$C$2:$C$341,ALL!A$2:A$341)<>"",_xlfn.XLOOKUP($C5,ALL!$C$2:$C$341,ALL!A$2:A$341),"") -> -156 | B5: =IF(_xlfn.XLOOKUP($C5,ALL!$C$2:$C$341,ALL!B$2:B$341)<>"",_xlfn.XLOOKUP($C5,ALL!$C$2:$C$341,ALL!B$2:B$341),"") -> FALSE | C5: Paransh Associates Private Limited | D5: =IF(_xlfn.XLOOKUP($C5,ALL!$C$2:$C$341,ALL!D$2:D$341)<>"",_xlfn.XLOOKUP($C5,ALL!$C$2:$C$341,ALL!D$2:D$341),"") | E5: =IF(_xlfn.XLOOKUP($C5,ALL!$C$2:$C$341,ALL!F$2:F$341)<>"",_xlfn.XLOOKUP($C5,ALL!$C$2:$C$341,ALL!F$2:F$341),"") -> Pratik Prabhu | F5: =IF(_xlfn.XLOOKUP($C5,ALL!$C$2:$C$341,ALL!G$2:G$341)<>"",_xlfn.XLOOKUP($C5,ALL!$C$2:$C$341,ALL!G$2:G$341),"") -> Sudarshan Shreenivas | G5: =IF(_xlfn.XLOOKUP($C5,ALL!$C$2:$C$341,ALL!H$2:H$341)<>"",_xlfn.XLOOKUP($C5,ALL!$C$2:$C$341,ALL!H$2:H$341),"") -> 46107 | H5: =IF(_xlfn.XLOOKUP($C5,ALL!$C$2:$C$341,ALL!I$2:I$341)<>"",_xlfn.XLOOKUP($C5,ALL!$C$2:$C$341,ALL!I$2:I$341),"") -> IVR B+ /Negative; INC | I5: =IF(_xlfn.XLOOKUP($C5,ALL!$C$2:$C$341,ALL!J$2:J$341)<>"",_xlfn.XLOOKUP($C5,ALL!$C$2:$C$341,ALL!J$2:J$341),"") | J5: =IF(_xlfn.XLOOKUP($C5,ALL!$C$2:$C$341,ALL!K$2:K$341)<>"",_xlfn.XLOOKUP($C5,ALL!$C$2:$C$341,ALL!K$2:K$341),"") -> 46472 | K5: =IF(_xlfn.XLOOKUP($C5,ALL!$C$2:$C$341,ALL!L$2:L$341)<>"",_xlfn.XLOOKUP($C5,ALL!$C$2:$C$341,ALL!L$2:L$341),"") -> Devrishi Viyan - 9969522952, Mr Mayank Agarwalla - 7760022929, Ritesh - 9810500076 | L5: =IF(_xlfn.XLOOKUP($C5,ALL!$C$2:$C$341,ALL!M$2:M$341)<>"",_xlfn.XLOOKUP($C5,ALL!$C$2:$C$341,ALL!M$2:M$341),"") | ... N5: =IF(_xlfn.XLOOKUP($C5,ALL!$C$2:$C$341,ALL!O$2:O$341)<>"",_xlfn.XLOOKUP($C5,ALL!$C$2:$C$341,ALL!O$2:O$341),"")
A6: =IF(_xlfn.XLOOKUP($C6,ALL!$C$2:$C$341,ALL!A$2:A$341)<>"",_xlfn.XLOOKUP($C6,ALL!$C$2:$C$341,ALL!A$2:A$341),"") -> -160 | B6: =IF(_xlfn.XLOOKUP($C6,ALL!$C$2:$C$341,ALL!B$2:B$341)<>"",_xlfn.XLOOKUP($C6,ALL!$C$2:$C$341,ALL!B$2:B$341),"") -> FALSE | C6: Sai Srushti Kengeri Projects Pvt Ltd | D6: =IF(_xlfn.XLOOKUP($C6,ALL!$C$2:$C$341,ALL!D$2:D$341)<>"",_xlfn.XLOOKUP($C6,ALL!$C$2:$C$341,ALL!D$2:D$341),"") | E6: =IF(_xlfn.XLOOKUP($C6,ALL!$C$2:$C$341,ALL!F$2:F$341)<>"",_xlfn.XLOOKUP($C6,ALL!$C$2:$C$341,ALL!F$2:F$341),"") -> Nikita | F6: =IF(_xlfn.XLOOKUP($C6,ALL!$C$2:$C$341,ALL!G$2:G$341)<>"",_xlfn.XLOOKUP($C6,ALL!$C$2:$C$341,ALL!G$2:G$341),"") -> Jyotsna | G6: =IF(_xlfn.XLOOKUP($C6,ALL!$C$2:$C$341,ALL!H$2:H$341)<>"",_xlfn.XLOOKUP($C6,ALL!$C$2:$C$341,ALL!H$2:H$341),"") -> 46111 | H6: =IF(_xlfn.XLOOKUP($C6,ALL!$C$2:$C$341,ALL!I$2:I$341)<>"",_xlfn.XLOOKUP($C6,ALL!$C$2:$C$341,ALL!I$2:I$341),"") -> IVR D; INC | I6: =IF(_xlfn.XLOOKUP($C6,ALL!$C$2:$C$341,ALL!J$2:J$341)<>"",_xlfn.XLOOKUP($C6,ALL!$C$2:$C$341,ALL!J$2:J$341),"") | J6: =IF(_xlfn.XLOOKUP($C6,ALL!$C$2:$C$341,ALL!K$2:K$341)<>"",_xlfn.XLOOKUP($C6,ALL!$C$2:$C$341,ALL!K$2:K$341),"") -> 46476 | K6: =IF(_xlfn.XLOOKUP($C6,ALL!$C$2:$C$341,ALL!L$2:L$341)<>"",_xlfn.XLOOKUP($C6,ALL!$C$2:$C$341,ALL!L$2:L$341),"") -> Nagamuni Reddy | L6: =IF(_xlfn.XLOOKUP($C6,ALL!$C$2:$C$341,ALL!M$2:M$341)<>"",_xlfn.XLOOKUP($C6,ALL!$C$2:$C$341,ALL!M$2:M$341),"") -> 9663692990 | ... N6: =IF(_xlfn.XLOOKUP($C6,ALL!$C$2:$C$341,ALL!O$2:O$341)<>"",_xlfn.XLOOKUP($C6,ALL!$C$2:$C$341,ALL!O$2:O$341),"")
A7: =IF(_xlfn.XLOOKUP($C7,ALL!$C$2:$C$341,ALL!A$2:A$341)<>"",_xlfn.XLOOKUP($C7,ALL!$C$2:$C$341,ALL!A$2:A$341),"") -> -175 | B7: =IF(_xlfn.XLOOKUP($C7,ALL!$C$2:$C$341,ALL!B$2:B$341)<>"",_xlfn.XLOOKUP($C7,ALL!$C$2:$C$341,ALL!B$2:B$341),"") -> FALSE | C7: Sai Srusti Bidalur Projects Pvt ltd | D7: =IF(_xlfn.XLOOKUP($C7,ALL!$C$2:$C$341,ALL!D$2:D$341)<>"",_xlfn.XLOOKUP($C7,ALL!$C$2:$C$341,ALL!D$2:D$341),"") | E7: =IF(_xlfn.XLOOKUP($C7,ALL!$C$2:$C$341,ALL!F$2:F$341)<>"",_xlfn.XLOOKUP($C7,ALL!$C$2:$C$341,ALL!F$2:F$341),"") -> Nikita | F7: =IF(_xlfn.XLOOKUP($C7,ALL!$C$2:$C$341,ALL!G$2:G$341)<>"",_xlfn.XLOOKUP($C7,ALL!$C$2:$C$341,ALL!G$2:G$341),"") -> Jyotsna | G7: =IF(_xlfn.XLOOKUP($C7,ALL!$C$2:$C$341,ALL!H$2:H$341)<>"",_xlfn.XLOOKUP($C7,ALL!$C$2:$C$341,ALL!H$2:H$341),"") -> 46126 | H7: =IF(_xlfn.XLOOKUP($C7,ALL!$C$2:$C$341,ALL!I$2:I$341)<>"",_xlfn.XLOOKUP($C7,ALL!$C$2:$C$341,ALL!I$2:I$341),"") -> IVR B- /Negative; INC | I7: =IF(_xlfn.XLOOKUP($C7,ALL!$C$2:$C$341,ALL!J$2:J$341)<>"",_xlfn.XLOOKUP($C7,ALL!$C$2:$C$341,ALL!J$2:J$341),"") | J7: =IF(_xlfn.XLOOKUP($C7,ALL!$C$2:$C$341,ALL!K$2:K$341)<>"",_xlfn.XLOOKUP($C7,ALL!$C$2:$C$341,ALL!K$2:K$341),"") -> 46491 | K7: =IF(_xlfn.XLOOKUP($C7,ALL!$C$2:$C$341,ALL!L$2:L$341)<>"",_xlfn.XLOOKUP($C7,ALL!$C$2:$C$341,ALL!L$2:L$341),"") -> Nagamuni Reddy | L7: =IF(_xlfn.XLOOKUP($C7,ALL!$C$2:$C$341,ALL!M$2:M$341)<>"",_xlfn.XLOOKUP($C7,ALL!$C$2:$C$341,ALL!M$2:M$341),"") -> 9663692990 | ... N7: =IF(_xlfn.XLOOKUP($C7,ALL!$C$2:$C$341,ALL!O$2:O$341)<>"",_xlfn.XLOOKUP($C7,ALL!$C$2:$C$341,ALL!O$2:O$341),"")
A8: =IF(_xlfn.XLOOKUP($C8,ALL!$C$2:$C$341,ALL!A$2:A$341)<>"",_xlfn.XLOOKUP($C8,ALL!$C$2:$C$341,ALL!A$2:A$341),"") -> -245 | B8: =IF(_xlfn.XLOOKUP($C8,ALL!$C$2:$C$341,ALL!B$2:B$341)<>"",_xlfn.XLOOKUP($C8,ALL!$C$2:$C$341,ALL!B$2:B$341),"") -> TRUE | C8: Radius and Deserve Land Developers Private Limited (NCD | D8: =IF(_xlfn.XLOOKUP($C8,ALL!$C$2:$C$341,ALL!D$2:D$341)<>"",_xlfn.XLOOKUP($C8,ALL!$C$2:$C$341,ALL!D$2:D$341),"") -> 302 | E8: =IF(_xlfn.XLOOKUP($C8,ALL!$C$2:$C$341,ALL!F$2:F$341)<>"",_xlfn.XLOOKUP($C8,ALL!$C$2:$C$341,ALL!F$2:F$341),"") -> Shubham Hande | F8: =IF(_xlfn.XLOOKUP($C8,ALL!$C$2:$C$341,ALL!G$2:G$341)<>"",_xlfn.XLOOKUP($C8,ALL!$C$2:$C$341,ALL!G$2:G$341),"") -> Amey Joshi | G8: =IF(_xlfn.XLOOKUP($C8,ALL!$C$2:$C$341,ALL!H$2:H$341)<>"",_xlfn.XLOOKUP($C8,ALL!$C$2:$C$341,ALL!H$2:H$341),"") -> 46196 | H8: =IF(_xlfn.XLOOKUP($C8,ALL!$C$2:$C$341,ALL!I$2:I$341)<>"",_xlfn.XLOOKUP($C8,ALL!$C$2:$C$341,ALL!I$2:I$341),"") -> IVR D (INC) | I8: =IF(_xlfn.XLOOKUP($C8,ALL!$C$2:$C$341,ALL!J$2:J$341)<>"",_xlfn.XLOOKUP($C8,ALL!$C$2:$C$341,ALL!J$2:J$341),"") -> NA | J8: =IF(_xlfn.XLOOKUP($C8,ALL!$C$2:$C$341,ALL!K$2:K$341)<>"",_xlfn.XLOOKUP($C8,ALL!$C$2:$C$341,ALL!K$2:K$341),"") -> 46561 | K8: =IF(_xlfn.XLOOKUP($C8,ALL!$C$2:$C$341,ALL!L$2:L$341)<>"",_xlfn.XLOOKUP($C8,ALL!$C$2:$C$341,ALL!L$2:L$341),"") -> - | L8: =IF(_xlfn.XLOOKUP($C8,ALL!$C$2:$C$341,ALL!M$2:M$341)<>"",_xlfn.XLOOKUP($C8,ALL!$C$2:$C$341,ALL!M$2:M$341),"") -> - | ... N8: =IF(_xlfn.XLOOKUP($C8,ALL!$C$2:$C$341,ALL!O$2:O$341)<>"",_xlfn.XLOOKUP($C8,ALL!$C$2:$C$341,ALL!O$2:O$341),"")
A9: =IF(_xlfn.XLOOKUP($C9,ALL!$C$2:$C$341,ALL!A$2:A$341)<>"",_xlfn.XLOOKUP($C9,ALL!$C$2:$C$341,ALL!A$2:A$341),"") -> -258 | B9: =IF(_xlfn.XLOOKUP($C9,ALL!$C$2:$C$341,ALL!B$2:B$341)<>"",_xlfn.XLOOKUP($C9,ALL!$C$2:$C$341,ALL!B$2:B$341),"") -> TRUE | C9: Primacy Industries Private Limited | D9: =IF(_xlfn.XLOOKUP($C9,ALL!$C$2:$C$341,ALL!D$2:D$341)<>"",_xlfn.XLOOKUP($C9,ALL!$C$2:$C$341,ALL!D$2:D$341),"") -> 82.38 | E9: =IF(_xlfn.XLOOKUP($C9,ALL!$C$2:$C$341,ALL!F$2:F$341)<>"",_xlfn.XLOOKUP($C9,ALL!$C$2:$C$341,ALL!F$2:F$341),"") -> Pratik Prabhu | F9: =IF(_xlfn.XLOOKUP($C9,ALL!$C$2:$C$341,ALL!G$2:G$341)<>"",_xlfn.XLOOKUP($C9,ALL!$C$2:$C$341,ALL!G$2:G$341),"") -> Sudarshan Shreenivas | G9: =IF(_xlfn.XLOOKUP($C9,ALL!$C$2:$C$341,ALL!H$2:H$341)<>"",_xlfn.XLOOKUP($C9,ALL!$C$2:$C$341,ALL!H$2:H$341),"") -> 46209 | H9: =IF(_xlfn.XLOOKUP($C9,ALL!$C$2:$C$341,ALL!I$2:I$341)<>"",_xlfn.XLOOKUP($C9,ALL!$C$2:$C$341,ALL!I$2:I$341),"") -> IVR B+ /Negative; INC | I9: =IF(_xlfn.XLOOKUP($C9,ALL!$C$2:$C$341,ALL!J$2:J$341)<>"",_xlfn.XLOOKUP($C9,ALL!$C$2:$C$341,ALL!J$2:J$341),"") | J9: =IF(_xlfn.XLOOKUP($C9,ALL!$C$2:$C$341,ALL!K$2:K$341)<>"",_xlfn.XLOOKUP($C9,ALL!$C$2:$C$341,ALL!K$2:K$341),"") -> 46574 | K9: =IF(_xlfn.XLOOKUP($C9,ALL!$C$2:$C$341,ALL!L$2:L$341)<>"",_xlfn.XLOOKUP($C9,ALL!$C$2:$C$341,ALL!L$2:L$341),"") -> 1. Ms. Sowmya Nayak – Mobile no : 9880942696 , 2. Mr. Renjith RS – Mobile no.: 7625092517 , 5. Ms. Reshmi Nair– Mobile no. : 9970747234 | L9: =IF(_xlfn.XLOOKUP($C9,ALL!$C$2:$C$341,ALL!M$2:M$341)<>"",_xlfn.XLOOKUP($C9,ALL!$C$2:$C$341,ALL!M$2:M$341),"") | ... N9: =IF(_xlfn.XLOOKUP($C9,ALL!$C$2:$C$341,ALL!O$2:O$341)<>"",_xlfn.XLOOKUP($C9,ALL!$C$2:$C$341,ALL!O$2:O$341),"")
A10: =IF(_xlfn.XLOOKUP($C10,ALL!$C$2:$C$341,ALL!A$2:A$341)<>"",_xlfn.XLOOKUP($C10,ALL!$C$2:$C$341,ALL!A$2:A$341),"") -> -288 | B10: =IF(_xlfn.XLOOKUP($C10,ALL!$C$2:$C$341,ALL!B$2:B$341)<>"",_xlfn.XLOOKUP($C10,ALL!$C$2:$C$341,ALL!B$2:B$341),"") -> TRUE | C10: Inditrade Microfinance Limited | D10: =IF(_xlfn.XLOOKUP($C10,ALL!$C$2:$C$341,ALL!D$2:D$341)<>"",_xlfn.XLOOKUP($C10,ALL!$C$2:$C$341,ALL!D$2:D$341),"") -> 60 | E10: =IF(_xlfn.XLOOKUP($C10,ALL!$C$2:$C$341,ALL!F$2:F$341)<>"",_xlfn.XLOOKUP($C10,ALL!$C$2:$C$341,ALL!F$2:F$341),"") -> Manan | F10: =IF(_xlfn.XLOOKUP($C10,ALL!$C$2:$C$341,ALL!G$2:G$341)<>"",_xlfn.XLOOKUP($C10,ALL!$C$2:$C$341,ALL!G$2:G$341),"") -> Amey Joshi | G10: =IF(_xlfn.XLOOKUP($C10,ALL!$C$2:$C$341,ALL!H$2:H$341)<>"",_xlfn.XLOOKUP($C10,ALL!$C$2:$C$341,ALL!H$2:H$341),"") -> 46239 | H10: =IF(_xlfn.XLOOKUP($C10,ALL!$C$2:$C$341,ALL!I$2:I$341)<>"",_xlfn.XLOOKUP($C10,ALL!$C$2:$C$341,ALL!I$2:I$341),"") -> IVR D; INC | I10: =IF(_xlfn.XLOOKUP($C10,ALL!$C$2:$C$341,ALL!J$2:J$341)<>"",_xlfn.XLOOKUP($C10,ALL!$C$2:$C$341,ALL!J$2:J$341),"") -> IVR D; INC | J10: =IF(_xlfn.XLOOKUP($C10,ALL!$C$2:$C$341,ALL!K$2:K$341)<>"",_xlfn.XLOOKUP($C10,ALL!$C$2:$C$341,ALL!K$2:K$341),"") -> 46604 | K10: =IF(_xlfn.XLOOKUP($C10,ALL!$C$2:$C$341,ALL!L$2:L$341)<>"",_xlfn.XLOOKUP($C10,ALL!$C$2:$C$341,ALL!L$2:L$341),"") -> KAPIL GUPTA | L10: =IF(_xlfn.XLOOKUP($C10,ALL!$C$2:$C$341,ALL!M$2:M$341)<>"",_xlfn.XLOOKUP($C10,ALL!$C$2:$C$341,ALL!M$2:M$341),"") -> 9324943984 | ... N10: =IF(_xlfn.XLOOKUP($C10,ALL!$C$2:$C$341,ALL!O$2:O$341)<>"",_xlfn.XLOOKUP($C10,ALL!$C$2:$C$341,ALL!O$2:O$341),"")
A11: =IF(_xlfn.XLOOKUP($C11,ALL!$C$2:$C$341,ALL!A$2:A$341)<>"",_xlfn.XLOOKUP($C11,ALL!$C$2:$C$341,ALL!A$2:A$341),"") -> -289 | B11: =IF(_xlfn.XLOOKUP($C11,ALL!$C$2:$C$341,ALL!B$2:B$341)<>"",_xlfn.XLOOKUP($C11,ALL!$C$2:$C$341,ALL!B$2:B$341),"") -> TRUE | C11: Aristo Securities Private Limited | D11: =IF(_xlfn.XLOOKUP($C11,ALL!$C$2:$C$341,ALL!D$2:D$341)<>"",_xlfn.XLOOKUP($C11,ALL!$C$2:$C$341,ALL!D$2:D$341),"") -> 547.47 | E11: =IF(_xlfn.XLOOKUP($C11,ALL!$C$2:$C$341,ALL!F$2:F$341)<>"",_xlfn.XLOOKUP($C11,ALL!$C$2:$C$341,ALL!F$2:F$341),"") -> Rahul Kadwe | F11: =IF(_xlfn.XLOOKUP($C11,ALL!$C$2:$C$341,ALL!G$2:G$341)<>"",_xlfn.XLOOKUP($C11,ALL!$C$2:$C$341,ALL!G$2:G$341),"") -> Amey Joshi | G11: =IF(_xlfn.XLOOKUP($C11,ALL!$C$2:$C$341,ALL!H$2:H$341)<>"",_xlfn.XLOOKUP($C11,ALL!$C$2:$C$341,ALL!H$2:H$341),"") -> 46240 | H11: =IF(_xlfn.XLOOKUP($C11,ALL!$C$2:$C$341,ALL!I$2:I$341)<>"",_xlfn.XLOOKUP($C11,ALL!$C$2:$C$341,ALL!I$2:I$341),"") -> IVR D; INC | I11: =IF(_xlfn.XLOOKUP($C11,ALL!$C$2:$C$341,ALL!J$2:J$341)<>"",_xlfn.XLOOKUP($C11,ALL!$C$2:$C$341,ALL!J$2:J$341),"") -> IVR D; INC | J11: =IF(_xlfn.XLOOKUP($C11,ALL!$C$2:$C$341,ALL!K$2:K$341)<>"",_xlfn.XLOOKUP($C11,ALL!$C$2:$C$341,ALL!K$2:K$341),"") -> 46605 | K11: =IF(_xlfn.XLOOKUP($C11,ALL!$C$2:$C$341,ALL!L$2:L$341)<>"",_xlfn.XLOOKUP($C11,ALL!$C$2:$C$341,ALL!L$2:L$341),"") -> Angela Sarna | L11: =IF(_xlfn.XLOOKUP($C11,ALL!$C$2:$C$341,ALL!M$2:M$341)<>"",_xlfn.XLOOKUP($C11,ALL!$C$2:$C$341,ALL!M$2:M$341),"") -> 9582704847 | ... N11: =IF(_xlfn.XLOOKUP($C11,ALL!$C$2:$C$341,ALL!O$2:O$341)<>"",_xlfn.XLOOKUP($C11,ALL!$C$2:$C$341,ALL!O$2:O$341),"")
A12: =IF(_xlfn.XLOOKUP($C12,ALL!$C$2:$C$341,ALL!A$2:A$341)<>"",_xlfn.XLOOKUP($C12,ALL!$C$2:$C$341,ALL!A$2:A$341),"") -> -290 | B12: =IF(_xlfn.XLOOKUP($C12,ALL!$C$2:$C$341,ALL!B$2:B$341)<>"",_xlfn.XLOOKUP($C12,ALL!$C$2:$C$341,ALL!B$2:B$341),"") -> TRUE | C12: Valencia and Mishal Ventures Private Limited | D12: =IF(_xlfn.XLOOKUP($C12,ALL!$C$2:$C$341,ALL!D$2:D$341)<>"",_xlfn.XLOOKUP($C12,ALL!$C$2:$C$341,ALL!D$2:D$341),"") -> 50 | E12: =IF(_xlfn.XLOOKUP($C12,ALL!$C$2:$C$341,ALL!F$2:F$341)<>"",_xlfn.XLOOKUP($C12,ALL!$C$2:$C$341,ALL!F$2:F$341),"") -> Nilesh Gupta | F12: =IF(_xlfn.XLOOKUP($C12,ALL!$C$2:$C$341,ALL!G$2:G$341)<>"",_xlfn.XLOOKUP($C12,ALL!$C$2:$C$341,ALL!G$2:G$341),"") -> Amey Joshi | G12: =IF(_xlfn.XLOOKUP($C12,ALL!$C$2:$C$341,ALL!H$2:H$341)<>"",_xlfn.XLOOKUP($C12,ALL!$C$2:$C$341,ALL!H$2:H$341),"") -> 46241 | H12: =IF(_xlfn.XLOOKUP($C12,ALL!$C$2:$C$341,ALL!I$2:I$341)<>"",_xlfn.XLOOKUP($C12,ALL!$C$2:$C$341,ALL!I$2:I$341),"") -> IVR D; INC | I12: =IF(_xlfn.XLOOKUP($C12,ALL!$C$2:$C$341,ALL!J$2:J$341)<>"",_xlfn.XLOOKUP($C12,ALL!$C$2:$C$341,ALL!J$2:J$341),"") | J12: =IF(_xlfn.XLOOKUP($C12,ALL!$C$2:$C$341,ALL!K$2:K$341)<>"",_xlfn.XLOOKUP($C12,ALL!$C$2:$C$341,ALL!K$2:K$341),"") -> 46606 | K12: =IF(_xlfn.XLOOKUP($C12,ALL!$C$2:$C$341,ALL!L$2:L$341)<>"",_xlfn.XLOOKUP($C12,ALL!$C$2:$C$341,ALL!L$2:L$341),"") | L12: =IF(_xlfn.XLOOKUP($C12,ALL!$C$2:$C$341,ALL!M$2:M$341)<>"",_xlfn.XLOOKUP($C12,ALL!$C$2:$C$341,ALL!M$2:M$341),"") | ... N12: =IF(_xlfn.XLOOKUP($C12,ALL!$C$2:$C$341,ALL!O$2:O$341)<>"",_xlfn.XLOOKUP($C12,ALL!$C$2:$C$341,ALL!O$2:O$341),"")
A13: =IF(_xlfn.XLOOKUP($C13,ALL!$C$2:$C$341,ALL!A$2:A$341)<>"",_xlfn.XLOOKUP($C13,ALL!$C$2:$C$341,ALL!A$2:A$341),"") -> -324 | B13: =IF(_xlfn.XLOOKUP($C13,ALL!$C$2:$C$341,ALL!B$2:B$341)<>"",_xlfn.XLOOKUP($C13,ALL!$C$2:$C$341,ALL!B$2:B$341),"") -> TRUE | C13: Arthmate Financing India Private Limited | D13: =IF(_xlfn.XLOOKUP($C13,ALL!$C$2:$C$341,ALL!D$2:D$341)<>"",_xlfn.XLOOKUP($C13,ALL!$C$2:$C$341,ALL!D$2:D$341),"") -> 276.77 | E13: =IF(_xlfn.XLOOKUP($C13,ALL!$C$2:$C$341,ALL!F$2:F$341)<>"",_xlfn.XLOOKUP($C13,ALL!$C$2:$C$341,ALL!F$2:F$341),"") -> Milan Purohit | F13: =IF(_xlfn.XLOOKUP($C13,ALL!$C$2:$C$341,ALL!G$2:G$341)<>"",_xlfn.XLOOKUP($C13,ALL!$C$2:$C$341,ALL!G$2:G$341),"") -> Amey Joshi | G13: =IF(_xlfn.XLOOKUP($C13,ALL!$C$2:$C$341,ALL!H$2:H$341)<>"",_xlfn.XLOOKUP($C13,ALL!$C$2:$C$341,ALL!H$2:H$341),"") -> 46275 | H13: =IF(_xlfn.XLOOKUP($C13,ALL!$C$2:$C$341,ALL!I$2:I$341)<>"",_xlfn.XLOOKUP($C13,ALL!$C$2:$C$341,ALL!I$2:I$341),"") -> IVR D; INC | I13: =IF(_xlfn.XLOOKUP($C13,ALL!$C$2:$C$341,ALL!J$2:J$341)<>"",_xlfn.XLOOKUP($C13,ALL!$C$2:$C$341,ALL!J$2:J$341),"") | J13: =IF(_xlfn.XLOOKUP($C13,ALL!$C$2:$C$341,ALL!K$2:K$341)<>"",_xlfn.XLOOKUP($C13,ALL!$C$2:$C$341,ALL!K$2:K$341),"") -> 46640 | K13: =IF(_xlfn.XLOOKUP($C13,ALL!$C$2:$C$341,ALL!L$2:L$341)<>"",_xlfn.XLOOKUP($C13,ALL!$C$2:$C$341,ALL!L$2:L$341),"") | L13: =IF(_xlfn.XLOOKUP($C13,ALL!$C$2:$C$341,ALL!M$2:M$341)<>"",_xlfn.XLOOKUP($C13,ALL!$C$2:$C$341,ALL!M$2:M$341),"") | ... N13: =IF(_xlfn.XLOOKUP($C13,ALL!$C$2:$C$341,ALL!O$2:O$341)<>"",_xlfn.XLOOKUP($C13,ALL!$C$2:$C$341,ALL!O$2:O$341),"")
A14: =IF(_xlfn.XLOOKUP($C14,ALL!$C$2:$C$341,ALL!A$2:A$341)<>"",_xlfn.XLOOKUP($C14,ALL!$C$2:$C$341,ALL!A$2:A$341),"") -> -330 | B14: =IF(_xlfn.XLOOKUP($C14,ALL!$C$2:$C$341,ALL!B$2:B$341)<>"",_xlfn.XLOOKUP($C14,ALL!$C$2:$C$341,ALL!B$2:B$341),"") -> TRUE | C14: Share India Securities Limited | D14: =IF(_xlfn.XLOOKUP($C14,ALL!$C$2:$C$341,ALL!D$2:D$341)<>"",_xlfn.XLOOKUP($C14,ALL!$C$2:$C$341,ALL!D$2:D$341),"") -> 1800 | E14: =IF(_xlfn.XLOOKUP($C14,ALL!$C$2:$C$341,ALL!F$2:F$341)<>"",_xlfn.XLOOKUP($C14,ALL!$C$2:$C$341,ALL!F$2:F$341),"") -> Milan Purohit | F14: =IF(_xlfn.XLOOKUP($C14,ALL!$C$2:$C$341,ALL!G$2:G$341)<>"",_xlfn.XLOOKUP($C14,ALL!$C$2:$C$341,ALL!G$2:G$341),"") -> Amey Joshi | G14: =IF(_xlfn.XLOOKUP($C14,ALL!$C$2:$C$341,ALL!H$2:H$341)<>"",_xlfn.XLOOKUP($C14,ALL!$C$2:$C$341,ALL!H$2:H$341),"") -> 46281 | H14: =IF(_xlfn.XLOOKUP($C14,ALL!$C$2:$C$341,ALL!I$2:I$341)<>"",_xlfn.XLOOKUP($C14,ALL!$C$2:$C$341,ALL!I$2:I$341),"") | I14: =IF(_xlfn.XLOOKUP($C14,ALL!$C$2:$C$341,ALL!J$2:J$341)<>"",_xlfn.XLOOKUP($C14,ALL!$C$2:$C$341,ALL!J$2:J$341),"") -> IVR A4; INC | J14: =IF(_xlfn.XLOOKUP($C14,ALL!$C$2:$C$341,ALL!K$2:K$341)<>"",_xlfn.XLOOKUP($C14,ALL!$C$2:$C$341,ALL!K$2:K$341),"") -> 46646 | K14: =IF(_xlfn.XLOOKUP($C14,ALL!$C$2:$C$341,ALL!L$2:L$341)<>"",_xlfn.XLOOKUP($C14,ALL!$C$2:$C$341,ALL!L$2:L$341),"") -> Ashish Sharma | L14: =IF(_xlfn.XLOOKUP($C14,ALL!$C$2:$C$341,ALL!M$2:M$341)<>"",_xlfn.XLOOKUP($C14,ALL!$C$2:$C$341,ALL!M$2:M$341),"") | ... N14: =IF(_xlfn.XLOOKUP($C14,ALL!$C$2:$C$341,ALL!O$2:O$341)<>"",_xlfn.XLOOKUP($C14,ALL!$C$2:$C$341,ALL!O$2:O$341),"")
A15: =IF(_xlfn.XLOOKUP($C15,ALL!$C$2:$C$341,ALL!A$2:A$341)<>"",_xlfn.XLOOKUP($C15,ALL!$C$2:$C$341,ALL!A$2:A$341),"") -> -330 | B15: =IF(_xlfn.XLOOKUP($C15,ALL!$C$2:$C$341,ALL!B$2:B$341)<>"",_xlfn.XLOOKUP($C15,ALL!$C$2:$C$341,ALL!B$2:B$341),"") -> TRUE | C15: Apollo Green Energy Limited | D15: =IF(_xlfn.XLOOKUP($C15,ALL!$C$2:$C$341,ALL!D$2:D$341)<>"",_xlfn.XLOOKUP($C15,ALL!$C$2:$C$341,ALL!D$2:D$341),"") -> 422.83 | E15: =IF(_xlfn.XLOOKUP($C15,ALL!$C$2:$C$341,ALL!F$2:F$341)<>"",_xlfn.XLOOKUP($C15,ALL!$C$2:$C$341,ALL!F$2:F$341),"") -> Rajsee Warang | F15: =IF(_xlfn.XLOOKUP($C15,ALL!$C$2:$C$341,ALL!G$2:G$341)<>"",_xlfn.XLOOKUP($C15,ALL!$C$2:$C$341,ALL!G$2:G$341),"") -> Jyotsna | G15: =IF(_xlfn.XLOOKUP($C15,ALL!$C$2:$C$341,ALL!H$2:H$341)<>"",_xlfn.XLOOKUP($C15,ALL!$C$2:$C$341,ALL!H$2:H$341),"") -> 46281 | H15: =IF(_xlfn.XLOOKUP($C15,ALL!$C$2:$C$341,ALL!I$2:I$341)<>"",_xlfn.XLOOKUP($C15,ALL!$C$2:$C$341,ALL!I$2:I$341),"") -> IVR D; INC | I15: =IF(_xlfn.XLOOKUP($C15,ALL!$C$2:$C$341,ALL!J$2:J$341)<>"",_xlfn.XLOOKUP($C15,ALL!$C$2:$C$341,ALL!J$2:J$341),"") -> IVR D; INC | J15: =IF(_xlfn.XLOOKUP($C15,ALL!$C$2:$C$341,ALL!K$2:K$341)<>"",_xlfn.XLOOKUP($C15,ALL!$C$2:$C$341,ALL!K$2:K$341),"") -> 46646 | K15: =IF(_xlfn.XLOOKUP($C15,ALL!$C$2:$C$341,ALL!L$2:L$341)<>"",_xlfn.XLOOKUP($C15,ALL!$C$2:$C$341,ALL!L$2:L$341),"") -> Manish Dhir and Rakesh Gupta | L15: =IF(_xlfn.XLOOKUP($C15,ALL!$C$2:$C$341,ALL!M$2:M$341)<>"",_xlfn.XLOOKUP($C15,ALL!$C$2:$C$341,ALL!M$2:M$341),"") -> 9823861621 and 9810091515 | M15: =IF(_xlfn.XLOOKUP($C15,ALL!$C$2:$C$341,ALL!N$2:N$341)<>"",_xlfn.XLOOKUP($C15,ALL!$C$2:$C$341,ALL!N$2:N$341),"") -> r.k.gupta@apolloindia.com
A16: =IF(_xlfn.XLOOKUP($C16,ALL!$C$2:$C$341,ALL!A$2:A$341)<>"",_xlfn.XLOOKUP($C16,ALL!$C$2:$C$341,ALL!A$2:A$341),"") -> Live | B16: =IF(_xlfn.XLOOKUP($C16,ALL!$C$2:$C$341,ALL!B$2:B$341)<>"",_xlfn.XLOOKUP($C16,ALL!$C$2:$C$341,ALL!B$2:B$341),"") -> FALSE | C16: ICL Fincorp Limited | D16: =IF(_xlfn.XLOOKUP($C16,ALL!$C$2:$C$341,ALL!D$2:D$341)<>"",_xlfn.XLOOKUP($C16,ALL!$C$2:$C$341,ALL!D$2:D$341),"") | E16: =IF(_xlfn.XLOOKUP($C16,ALL!$C$2:$C$341,ALL!F$2:F$341)<>"",_xlfn.XLOOKUP($C16,ALL!$C$2:$C$341,ALL!F$2:F$341),"") -> Manan | F16: =IF(_xlfn.XLOOKUP($C16,ALL!$C$2:$C$341,ALL!G$2:G$341)<>"",_xlfn.XLOOKUP($C16,ALL!$C$2:$C$341,ALL!G$2:G$341),"") -> Amey Joshi | G16: =IF(_xlfn.XLOOKUP($C16,ALL!$C$2:$C$341,ALL!H$2:H$341)<>"",_xlfn.XLOOKUP($C16,ALL!$C$2:$C$341,ALL!H$2:H$341),"") | H16: =IF(_xlfn.XLOOKUP($C16,ALL!$C$2:$C$341,ALL!I$2:I$341)<>"",_xlfn.XLOOKUP($C16,ALL!$C$2:$C$341,ALL!I$2:I$341),"") -> IVR BB- INC | I16: =IF(_xlfn.XLOOKUP($C16,ALL!$C$2:$C$341,ALL!J$2:J$341)<>"",_xlfn.XLOOKUP($C16,ALL!$C$2:$C$341,ALL!J$2:J$341),"") | J16: =IF(_xlfn.XLOOKUP($C16,ALL!$C$2:$C$341,ALL!K$2:K$341)<>"",_xlfn.XLOOKUP($C16,ALL!$C$2:$C$341,ALL!K$2:K$341),"") | K16: =IF(_xlfn.XLOOKUP($C16,ALL!$C$2:$C$341,ALL!L$2:L$341)<>"",_xlfn.XLOOKUP($C16,ALL!$C$2:$C$341,ALL!L$2:L$341),"") -> Nikitha - Accts manager | L16: =IF(_xlfn.XLOOKUP($C16,ALL!$C$2:$C$341,ALL!M$2:M$341)<>"",_xlfn.XLOOKUP($C16,ALL!$C$2:$C$341,ALL!M$2:M$341),"") -> 8086928283 | ... N16: =IF(_xlfn.XLOOKUP($C16,ALL!$C$2:$C$341,ALL!O$2:O$341)<>"",_xlfn.XLOOKUP($C16,ALL!$C$2:$C$341,ALL!O$2:O$341),"")
A17: =IF(_xlfn.XLOOKUP($C17,ALL!$C$2:$C$341,ALL!A$2:A$341)<>"",_xlfn.XLOOKUP($C17,ALL!$C$2:$C$341,ALL!A$2:A$341),"") | B17: =IF(_xlfn.XLOOKUP($C17,ALL!$C$2:$C$341,ALL!B$2:B$341)<>"",_xlfn.XLOOKUP($C17,ALL!$C$2:$C$341,ALL!B$2:B$341),"") | D17: =IF(_xlfn.XLOOKUP($C17,ALL!$C$2:$C$341,ALL!D$2:D$341)<>"",_xlfn.XLOOKUP($C17,ALL!$C$2:$C$341,ALL!D$2:D$341),"") | E17: =IF(_xlfn.XLOOKUP($C17,ALL!$C$2:$C$341,ALL!F$2:F$341)<>"",_xlfn.XLOOKUP($C17,ALL!$C$2:$C$341,ALL!F$2:F$341),"") | F17: =IF(_xlfn.XLOOKUP($C17,ALL!$C$2:$C$341,ALL!G$2:G$341)<>"",_xlfn.XLOOKUP($C17,ALL!$C$2:$C$341,ALL!G$2:G$341),"") | G17: =IF(_xlfn.XLOOKUP($C17,ALL!$C$2:$C$341,ALL!H$2:H$341)<>"",_xlfn.XLOOKUP($C17,ALL!$C$2:$C$341,ALL!H$2:H$341),"") | H17: =IF(_xlfn.XLOOKUP($C17,ALL!$C$2:$C$341,ALL!I$2:I$341)<>"",_xlfn.XLOOKUP($C17,ALL!$C$2:$C$341,ALL!I$2:I$341),"") | I17: =IF(_xlfn.XLOOKUP($C17,ALL!$C$2:$C$341,ALL!J$2:J$341)<>"",_xlfn.XLOOKUP($C17,ALL!$C$2:$C$341,ALL!J$2:J$341),"") | J17: =IF(_xlfn.XLOOKUP($C17,ALL!$C$2:$C$341,ALL!K$2:K$341)<>"",_xlfn.XLOOKUP($C17,ALL!$C$2:$C$341,ALL!K$2:K$341),"") | K17: =IF(_xlfn.XLOOKUP($C17,ALL!$C$2:$C$341,ALL!L$2:L$341)<>"",_xlfn.XLOOKUP($C17,ALL!$C$2:$C$341,ALL!L$2:L$341),"") | L17: =IF(_xlfn.XLOOKUP($C17,ALL!$C$2:$C$341,ALL!M$2:M$341)<>"",_xlfn.XLOOKUP($C17,ALL!$C$2:$C$341,ALL!M$2:M$341),"") | ... N17: =IF(_xlfn.XLOOKUP($C17,ALL!$C$2:$C$341,ALL!O$2:O$341)<>"",_xlfn.XLOOKUP($C17,ALL!$C$2:$C$341,ALL!O$2:O$341),"")
A18: =IF(_xlfn.XLOOKUP($C18,ALL!$C$2:$C$341,ALL!A$2:A$341)<>"",_xlfn.XLOOKUP($C18,ALL!$C$2:$C$341,ALL!A$2:A$341),"") | B18: =IF(_xlfn.XLOOKUP($C18,ALL!$C$2:$C$341,ALL!B$2:B$341)<>"",_xlfn.XLOOKUP($C18,ALL!$C$2:$C$341,ALL!B$2:B$341),"") | D18: =IF(_xlfn.XLOOKUP($C18,ALL!$C$2:$C$341,ALL!D$2:D$341)<>"",_xlfn.XLOOKUP($C18,ALL!$C$2:$C$341,ALL!D$2:D$341),"") | E18: =IF(_xlfn.XLOOKUP($C18,ALL!$C$2:$C$341,ALL!F$2:F$341)<>"",_xlfn.XLOOKUP($C18,ALL!$C$2:$C$341,ALL!F$2:F$341),"") | F18: =IF(_xlfn.XLOOKUP($C18,ALL!$C$2:$C$341,ALL!G$2:G$341)<>"",_xlfn.XLOOKUP($C18,ALL!$C$2:$C$341,ALL!G$2:G$341),"") | G18: =IF(_xlfn.XLOOKUP($C18,ALL!$C$2:$C$341,ALL!H$2:H$341)<>"",_xlfn.XLOOKUP($C18,ALL!$C$2:$C$341,ALL!H$2:H$341),"") | H18: =IF(_xlfn.XLOOKUP($C18,ALL!$C$2:$C$341,ALL!I$2:I$341)<>"",_xlfn.XLOOKUP($C18,ALL!$C$2:$C$341,ALL!I$2:I$341),"") | I18: =IF(_xlfn.XLOOKUP($C18,ALL!$C$2:$C$341,ALL!J$2:J$341)<>"",_xlfn.XLOOKUP($C18,ALL!$C$2:$C$341,ALL!J$2:J$341),"") | J18: =IF(_xlfn.XLOOKUP($C18,ALL!$C$2:$C$341,ALL!K$2:K$341)<>"",_xlfn.XLOOKUP($C18,ALL!$C$2:$C$341,ALL!K$2:K$341),"") | K18: =IF(_xlfn.XLOOKUP($C18,ALL!$C$2:$C$341,ALL!L$2:L$341)<>"",_xlfn.XLOOKUP($C18,ALL!$C$2:$C$341,ALL!L$2:L$341),"") | L18: =IF(_xlfn.XLOOKUP($C18,ALL!$C$2:$C$341,ALL!M$2:M$341)<>"",_xlfn.XLOOKUP($C18,ALL!$C$2:$C$341,ALL!M$2:M$341),"") | ... N18: =IF(_xlfn.XLOOKUP($C18,ALL!$C$2:$C$341,ALL!O$2:O$341)<>"",_xlfn.XLOOKUP($C18,ALL!$C$2:$C$341,ALL!O$2:O$341),"")
A19: =IF(_xlfn.XLOOKUP($C19,ALL!$C$2:$C$341,ALL!A$2:A$341)<>"",_xlfn.XLOOKUP($C19,ALL!$C$2:$C$341,ALL!A$2:A$341),"") | B19: =IF(_xlfn.XLOOKUP($C19,ALL!$C$2:$C$341,ALL!B$2:B$341)<>"",_xlfn.XLOOKUP($C19,ALL!$C$2:$C$341,ALL!B$2:B$341),"") | D19: =IF(_xlfn.XLOOKUP($C19,ALL!$C$2:$C$341,ALL!D$2:D$341)<>"",_xlfn.XLOOKUP($C19,ALL!$C$2:$C$341,ALL!D$2:D$341),"") | E19: =IF(_xlfn.XLOOKUP($C19,ALL!$C$2:$C$341,ALL!F$2:F$341)<>"",_xlfn.XLOOKUP($C19,ALL!$C$2:$C$341,ALL!F$2:F$341),"") | F19: =IF(_xlfn.XLOOKUP($C19,ALL!$C$2:$C$341,ALL!G$2:G$341)<>"",_xlfn.XLOOKUP($C19,ALL!$C$2:$C$341,ALL!G$2:G$341),"") | G19: =IF(_xlfn.XLOOKUP($C19,ALL!$C$2:$C$341,ALL!H$2:H$341)<>"",_xlfn.XLOOKUP($C19,ALL!$C$2:$C$341,ALL!H$2:H$341),"") | H19: =IF(_xlfn.XLOOKUP($C19,ALL!$C$2:$C$341,ALL!I$2:I$341)<>"",_xlfn.XLOOKUP($C19,ALL!$C$2:$C$341,ALL!I$2:I$341),"") | I19: =IF(_xlfn.XLOOKUP($C19,ALL!$C$2:$C$341,ALL!J$2:J$341)<>"",_xlfn.XLOOKUP($C19,ALL!$C$2:$C$341,ALL!J$2:J$341),"") | J19: =IF(_xlfn.XLOOKUP($C19,ALL!$C$2:$C$341,ALL!K$2:K$341)<>"",_xlfn.XLOOKUP($C19,ALL!$C$2:$C$341,ALL!K$2:K$341),"") | K19: =IF(_xlfn.XLOOKUP($C19,ALL!$C$2:$C$341,ALL!L$2:L$341)<>"",_xlfn.XLOOKUP($C19,ALL!$C$2:$C$341,ALL!L$2:L$341),"") | L19: =IF(_xlfn.XLOOKUP($C19,ALL!$C$2:$C$341,ALL!M$2:M$341)<>"",_xlfn.XLOOKUP($C19,ALL!$C$2:$C$341,ALL!M$2:M$341),"") | ... N19: =IF(_xlfn.XLOOKUP($C19,ALL!$C$2:$C$341,ALL!O$2:O$341)<>"",_xlfn.XLOOKUP($C19,ALL!$C$2:$C$341,ALL!O$2:O$341),"")
A20: =IF(_xlfn.XLOOKUP($C20,ALL!$C$2:$C$341,ALL!A$2:A$341)<>"",_xlfn.XLOOKUP($C20,ALL!$C$2:$C$341,ALL!A$2:A$341),"") | B20: =IF(_xlfn.XLOOKUP($C20,ALL!$C$2:$C$341,ALL!B$2:B$341)<>"",_xlfn.XLOOKUP($C20,ALL!$C$2:$C$341,ALL!B$2:B$341),"") | D20: =IF(_xlfn.XLOOKUP($C20,ALL!$C$2:$C$341,ALL!D$2:D$341)<>"",_xlfn.XLOOKUP($C20,ALL!$C$2:$C$341,ALL!D$2:D$341),"") | E20: =IF(_xlfn.XLOOKUP($C20,ALL!$C$2:$C$341,ALL!F$2:F$341)<>"",_xlfn.XLOOKUP($C20,ALL!$C$2:$C$341,ALL!F$2:F$341),"") | F20: =IF(_xlfn.XLOOKUP($C20,ALL!$C$2:$C$341,ALL!G$2:G$341)<>"",_xlfn.XLOOKUP($C20,ALL!$C$2:$C$341,ALL!G$2:G$341),"") | G20: =IF(_xlfn.XLOOKUP($C20,ALL!$C$2:$C$341,ALL!H$2:H$341)<>"",_xlfn.XLOOKUP($C20,ALL!$C$2:$C$341,ALL!H$2:H$341),"") | H20: =IF(_xlfn.XLOOKUP($C20,ALL!$C$2:$C$341,ALL!I$2:I$341)<>"",_xlfn.XLOOKUP($C20,ALL!$C$2:$C$341,ALL!I$2:I$341),"") | I20: =IF(_xlfn.XLOOKUP($C20,ALL!$C$2:$C$341,ALL!J$2:J$341)<>"",_xlfn.XLOOKUP($C20,ALL!$C$2:$C$341,ALL!J$2:J$341),"") | J20: =IF(_xlfn.XLOOKUP($C20,ALL!$C$2:$C$341,ALL!K$2:K$341)<>"",_xlfn.XLOOKUP($C20,ALL!$C$2:$C$341,ALL!K$2:K$341),"") | K20: =IF(_xlfn.XLOOKUP($C20,ALL!$C$2:$C$341,ALL!L$2:L$341)<>"",_xlfn.XLOOKUP($C20,ALL!$C$2:$C$341,ALL!L$2:L$341),"") | L20: =IF(_xlfn.XLOOKUP($C20,ALL!$C$2:$C$341,ALL!M$2:M$341)<>"",_xlfn.XLOOKUP($C20,ALL!$C$2:$C$341,ALL!M$2:M$341),"") | ... N20: =IF(_xlfn.XLOOKUP($C20,ALL!$C$2:$C$341,ALL!O$2:O$341)<>"",_xlfn.XLOOKUP($C20,ALL!$C$2:$C$341,ALL!O$2:O$341),"")
A21: =IF(_xlfn.XLOOKUP($C21,ALL!$C$2:$C$341,ALL!A$2:A$341)<>"",_xlfn.XLOOKUP($C21,ALL!$C$2:$C$341,ALL!A$2:A$341),"") | B21: =IF(_xlfn.XLOOKUP($C21,ALL!$C$2:$C$341,ALL!B$2:B$341)<>"",_xlfn.XLOOKUP($C21,ALL!$C$2:$C$341,ALL!B$2:B$341),"") | D21: =IF(_xlfn.XLOOKUP($C21,ALL!$C$2:$C$341,ALL!D$2:D$341)<>"",_xlfn.XLOOKUP($C21,ALL!$C$2:$C$341,ALL!D$2:D$341),"") | E21: =IF(_xlfn.XLOOKUP($C21,ALL!$C$2:$C$341,ALL!F$2:F$341)<>"",_xlfn.XLOOKUP($C21,ALL!$C$2:$C$341,ALL!F$2:F$341),"") | F21: =IF(_xlfn.XLOOKUP($C21,ALL!$C$2:$C$341,ALL!G$2:G$341)<>"",_xlfn.XLOOKUP($C21,ALL!$C$2:$C$341,ALL!G$2:G$341),"") | G21: =IF(_xlfn.XLOOKUP($C21,ALL!$C$2:$C$341,ALL!H$2:H$341)<>"",_xlfn.XLOOKUP($C21,ALL!$C$2:$C$341,ALL!H$2:H$341),"") | H21: =IF(_xlfn.XLOOKUP($C21,ALL!$C$2:$C$341,ALL!I$2:I$341)<>"",_xlfn.XLOOKUP($C21,ALL!$C$2:$C$341,ALL!I$2:I$341),"") | I21: =IF(_xlfn.XLOOKUP($C21,ALL!$C$2:$C$341,ALL!J$2:J$341)<>"",_xlfn.XLOOKUP($C21,ALL!$C$2:$C$341,ALL!J$2:J$341),"") | J21: =IF(_xlfn.XLOOKUP($C21,ALL!$C$2:$C$341,ALL!K$2:K$341)<>"",_xlfn.XLOOKUP($C21,ALL!$C$2:$C$341,ALL!K$2:K$341),"") | K21: =IF(_xlfn.XLOOKUP($C21,ALL!$C$2:$C$341,ALL!L$2:L$341)<>"",_xlfn.XLOOKUP($C21,ALL!$C$2:$C$341,ALL!L$2:L$341),"") | L21: =IF(_xlfn.XLOOKUP($C21,ALL!$C$2:$C$341,ALL!M$2:M$341)<>"",_xlfn.XLOOKUP($C21,ALL!$C$2:$C$341,ALL!M$2:M$341),"") | ... N21: =IF(_xlfn.XLOOKUP($C21,ALL!$C$2:$C$341,ALL!O$2:O$341)<>"",_xlfn.XLOOKUP($C21,ALL!$C$2:$C$341,ALL!O$2:O$341),"")
A22: =IF(_xlfn.XLOOKUP($C22,ALL!$C$2:$C$341,ALL!A$2:A$341)<>"",_xlfn.XLOOKUP($C22,ALL!$C$2:$C$341,ALL!A$2:A$341),"") | B22: =IF(_xlfn.XLOOKUP($C22,ALL!$C$2:$C$341,ALL!B$2:B$341)<>"",_xlfn.XLOOKUP($C22,ALL!$C$2:$C$341,ALL!B$2:B$341),"") | D22: =IF(_xlfn.XLOOKUP($C22,ALL!$C$2:$C$341,ALL!D$2:D$341)<>"",_xlfn.XLOOKUP($C22,ALL!$C$2:$C$341,ALL!D$2:D$341),"") | E22: =IF(_xlfn.XLOOKUP($C22,ALL!$C$2:$C$341,ALL!F$2:F$341)<>"",_xlfn.XLOOKUP($C22,ALL!$C$2:$C$341,ALL!F$2:F$341),"") | F22: =IF(_xlfn.XLOOKUP($C22,ALL!$C$2:$C$341,ALL!G$2:G$341)<>"",_xlfn.XLOOKUP($C22,ALL!$C$2:$C$341,ALL!G$2:G$341),"") | G22: =IF(_xlfn.XLOOKUP($C22,ALL!$C$2:$C$341,ALL!H$2:H$341)<>"",_xlfn.XLOOKUP($C22,ALL!$C$2:$C$341,ALL!H$2:H$341),"") | H22: =IF(_xlfn.XLOOKUP($C22,ALL!$C$2:$C$341,ALL!I$2:I$341)<>"",_xlfn.XLOOKUP($C22,ALL!$C$2:$C$341,ALL!I$2:I$341),"") | I22: =IF(_xlfn.XLOOKUP($C22,ALL!$C$2:$C$341,ALL!J$2:J$341)<>"",_xlfn.XLOOKUP($C22,ALL!$C$2:$C$341,ALL!J$2:J$341),"") | J22: =IF(_xlfn.XLOOKUP($C22,ALL!$C$2:$C$341,ALL!K$2:K$341)<>"",_xlfn.XLOOKUP($C22,ALL!$C$2:$C$341,ALL!K$2:K$341),"") | K22: =IF(_xlfn.XLOOKUP($C22,ALL!$C$2:$C$341,ALL!L$2:L$341)<>"",_xlfn.XLOOKUP($C22,ALL!$C$2:$C$341,ALL!L$2:L$341),"") | L22: =IF(_xlfn.XLOOKUP($C22,ALL!$C$2:$C$341,ALL!M$2:M$341)<>"",_xlfn.XLOOKUP($C22,ALL!$C$2:$C$341,ALL!M$2:M$341),"") | ... N22: =IF(_xlfn.XLOOKUP($C22,ALL!$C$2:$C$341,ALL!O$2:O$341)<>"",_xlfn.XLOOKUP($C22,ALL!$C$2:$C$341,ALL!O$2:O$341),"")
A23: =IF(_xlfn.XLOOKUP($C23,ALL!$C$2:$C$341,ALL!A$2:A$341)<>"",_xlfn.XLOOKUP($C23,ALL!$C$2:$C$341,ALL!A$2:A$341),"") | B23: =IF(_xlfn.XLOOKUP($C23,ALL!$C$2:$C$341,ALL!B$2:B$341)<>"",_xlfn.XLOOKUP($C23,ALL!$C$2:$C$341,ALL!B$2:B$341),"") | D23: =IF(_xlfn.XLOOKUP($C23,ALL!$C$2:$C$341,ALL!D$2:D$341)<>"",_xlfn.XLOOKUP($C23,ALL!$C$2:$C$341,ALL!D$2:D$341),"") | E23: =IF(_xlfn.XLOOKUP($C23,ALL!$C$2:$C$341,ALL!F$2:F$341)<>"",_xlfn.XLOOKUP($C23,ALL!$C$2:$C$341,ALL!F$2:F$341),"") | F23: =IF(_xlfn.XLOOKUP($C23,ALL!$C$2:$C$341,ALL!G$2:G$341)<>"",_xlfn.XLOOKUP($C23,ALL!$C$2:$C$341,ALL!G$2:G$341),"") | G23: =IF(_xlfn.XLOOKUP($C23,ALL!$C$2:$C$341,ALL!H$2:H$341)<>"",_xlfn.XLOOKUP($C23,ALL!$C$2:$C$341,ALL!H$2:H$341),"") | H23: =IF(_xlfn.XLOOKUP($C23,ALL!$C$2:$C$341,ALL!I$2:I$341)<>"",_xlfn.XLOOKUP($C23,ALL!$C$2:$C$341,ALL!I$2:I$341),"") | I23: =IF(_xlfn.XLOOKUP($C23,ALL!$C$2:$C$341,ALL!J$2:J$341)<>"",_xlfn.XLOOKUP($C23,ALL!$C$2:$C$341,ALL!J$2:J$341),"") | J23: =IF(_xlfn.XLOOKUP($C23,ALL!$C$2:$C$341,ALL!K$2:K$341)<>"",_xlfn.XLOOKUP($C23,ALL!$C$2:$C$341,ALL!K$2:K$341),"") | K23: =IF(_xlfn.XLOOKUP($C23,ALL!$C$2:$C$341,ALL!L$2:L$341)<>"",_xlfn.XLOOKUP($C23,ALL!$C$2:$C$341,ALL!L$2:L$341),"") | L23: =IF(_xlfn.XLOOKUP($C23,ALL!$C$2:$C$341,ALL!M$2:M$341)<>"",_xlfn.XLOOKUP($C23,ALL!$C$2:$C$341,ALL!M$2:M$341),"") | ... N23: =IF(_xlfn.XLOOKUP($C23,ALL!$C$2:$C$341,ALL!O$2:O$341)<>"",_xlfn.XLOOKUP($C23,ALL!$C$2:$C$341,ALL!O$2:O$341),"")
A24: =IF(_xlfn.XLOOKUP($C24,ALL!$C$2:$C$341,ALL!A$2:A$341)<>"",_xlfn.XLOOKUP($C24,ALL!$C$2:$C$341,ALL!A$2:A$341),"") | B24: =IF(_xlfn.XLOOKUP($C24,ALL!$C$2:$C$341,ALL!B$2:B$341)<>"",_xlfn.XLOOKUP($C24,ALL!$C$2:$C$341,ALL!B$2:B$341),"") | D24: =IF(_xlfn.XLOOKUP($C24,ALL!$C$2:$C$341,ALL!D$2:D$341)<>"",_xlfn.XLOOKUP($C24,ALL!$C$2:$C$341,ALL!D$2:D$341),"") | E24: =IF(_xlfn.XLOOKUP($C24,ALL!$C$2:$C$341,ALL!F$2:F$341)<>"",_xlfn.XLOOKUP($C24,ALL!$C$2:$C$341,ALL!F$2:F$341),"") | F24: =IF(_xlfn.XLOOKUP($C24,ALL!$C$2:$C$341,ALL!G$2:G$341)<>"",_xlfn.XLOOKUP($C24,ALL!$C$2:$C$341,ALL!G$2:G$341),"") | G24: =IF(_xlfn.XLOOKUP($C24,ALL!$C$2:$C$341,ALL!H$2:H$341)<>"",_xlfn.XLOOKUP($C24,ALL!$C$2:$C$341,ALL!H$2:H$341),"") | H24: =IF(_xlfn.XLOOKUP($C24,ALL!$C$2:$C$341,ALL!I$2:I$341)<>"",_xlfn.XLOOKUP($C24,ALL!$C$2:$C$341,ALL!I$2:I$341),"") | I24: =IF(_xlfn.XLOOKUP($C24,ALL!$C$2:$C$341,ALL!J$2:J$341)<>"",_xlfn.XLOOKUP($C24,ALL!$C$2:$C$341,ALL!J$2:J$341),"") | J24: =IF(_xlfn.XLOOKUP($C24,ALL!$C$2:$C$341,ALL!K$2:K$341)<>"",_xlfn.XLOOKUP($C24,ALL!$C$2:$C$341,ALL!K$2:K$341),"") | K24: =IF(_xlfn.XLOOKUP($C24,ALL!$C$2:$C$341,ALL!L$2:L$341)<>"",_xlfn.XLOOKUP($C24,ALL!$C$2:$C$341,ALL!L$2:L$341),"") | L24: =IF(_xlfn.XLOOKUP($C24,ALL!$C$2:$C$341,ALL!M$2:M$341)<>"",_xlfn.XLOOKUP($C24,ALL!$C$2:$C$341,ALL!M$2:M$341),"") | ... N24: =IF(_xlfn.XLOOKUP($C24,ALL!$C$2:$C$341,ALL!O$2:O$341)<>"",_xlfn.XLOOKUP($C24,ALL!$C$2:$C$341,ALL!O$2:O$341),"")
A25: =IF(_xlfn.XLOOKUP($C25,ALL!$C$2:$C$341,ALL!A$2:A$341)<>"",_xlfn.XLOOKUP($C25,ALL!$C$2:$C$341,ALL!A$2:A$341),"") | B25: =IF(_xlfn.XLOOKUP($C25,ALL!$C$2:$C$341,ALL!B$2:B$341)<>"",_xlfn.XLOOKUP($C25,ALL!$C$2:$C$341,ALL!B$2:B$341),"") | D25: =IF(_xlfn.XLOOKUP($C25,ALL!$C$2:$C$341,ALL!D$2:D$341)<>"",_xlfn.XLOOKUP($C25,ALL!$C$2:$C$341,ALL!D$2:D$341),"") | E25: =IF(_xlfn.XLOOKUP($C25,ALL!$C$2:$C$341,ALL!F$2:F$341)<>"",_xlfn.XLOOKUP($C25,ALL!$C$2:$C$341,ALL!F$2:F$341),"") | F25: =IF(_xlfn.XLOOKUP($C25,ALL!$C$2:$C$341,ALL!G$2:G$341)<>"",_xlfn.XLOOKUP($C25,ALL!$C$2:$C$341,ALL!G$2:G$341),"") | G25: =IF(_xlfn.XLOOKUP($C25,ALL!$C$2:$C$341,ALL!H$2:H$341)<>"",_xlfn.XLOOKUP($C25,ALL!$C$2:$C$341,ALL!H$2:H$341),"") | H25: =IF(_xlfn.XLOOKUP($C25,ALL!$C$2:$C$341,ALL!I$2:I$341)<>"",_xlfn.XLOOKUP($C25,ALL!$C$2:$C$341,ALL!I$2:I$341),"") | I25: =IF(_xlfn.XLOOKUP($C25,ALL!$C$2:$C$341,ALL!J$2:J$341)<>"",_xlfn.XLOOKUP($C25,ALL!$C$2:$C$341,ALL!J$2:J$341),"") | J25: =IF(_xlfn.XLOOKUP($C25,ALL!$C$2:$C$341,ALL!K$2:K$341)<>"",_xlfn.XLOOKUP($C25,ALL!$C$2:$C$341,ALL!K$2:K$341),"") | K25: =IF(_xlfn.XLOOKUP($C25,ALL!$C$2:$C$341,ALL!L$2:L$341)<>"",_xlfn.XLOOKUP($C25,ALL!$C$2:$C$341,ALL!L$2:L$341),"") | L25: =IF(_xlfn.XLOOKUP($C25,ALL!$C$2:$C$341,ALL!M$2:M$341)<>"",_xlfn.XLOOKUP($C25,ALL!$C$2:$C$341,ALL!M$2:M$341),"") | ... N25: =IF(_xlfn.XLOOKUP($C25,ALL!$C$2:$C$341,ALL!O$2:O$341)<>"",_xlfn.XLOOKUP($C25,ALL!$C$2:$C$341,ALL!O$2:O$341),"")
A26: =IF(_xlfn.XLOOKUP($C26,ALL!$C$2:$C$341,ALL!A$2:A$341)<>"",_xlfn.XLOOKUP($C26,ALL!$C$2:$C$341,ALL!A$2:A$341),"") | B26: =IF(_xlfn.XLOOKUP($C26,ALL!$C$2:$C$341,ALL!B$2:B$341)<>"",_xlfn.XLOOKUP($C26,ALL!$C$2:$C$341,ALL!B$2:B$341),"") | D26: =IF(_xlfn.XLOOKUP($C26,ALL!$C$2:$C$341,ALL!D$2:D$341)<>"",_xlfn.XLOOKUP($C26,ALL!$C$2:$C$341,ALL!D$2:D$341),"") | E26: =IF(_xlfn.XLOOKUP($C26,ALL!$C$2:$C$341,ALL!F$2:F$341)<>"",_xlfn.XLOOKUP($C26,ALL!$C$2:$C$341,ALL!F$2:F$341),"") | F26: =IF(_xlfn.XLOOKUP($C26,ALL!$C$2:$C$341,ALL!G$2:G$341)<>"",_xlfn.XLOOKUP($C26,ALL!$C$2:$C$341,ALL!G$2:G$341),"") | G26: =IF(_xlfn.XLOOKUP($C26,ALL!$C$2:$C$341,ALL!H$2:H$341)<>"",_xlfn.XLOOKUP($C26,ALL!$C$2:$C$341,ALL!H$2:H$341),"") | H26: =IF(_xlfn.XLOOKUP($C26,ALL!$C$2:$C$341,ALL!I$2:I$341)<>"",_xlfn.XLOOKUP($C26,ALL!$C$2:$C$341,ALL!I$2:I$341),"") | I26: =IF(_xlfn.XLOOKUP($C26,ALL!$C$2:$C$341,ALL!J$2:J$341)<>"",_xlfn.XLOOKUP($C26,ALL!$C$2:$C$341,ALL!J$2:J$341),"") | J26: =IF(_xlfn.XLOOKUP($C26,ALL!$C$2:$C$341,ALL!K$2:K$341)<>"",_xlfn.XLOOKUP($C26,ALL!$C$2:$C$341,ALL!K$2:K$341),"") | K26: =IF(_xlfn.XLOOKUP($C26,ALL!$C$2:$C$341,ALL!L$2:L$341)<>"",_xlfn.XLOOKUP($C26,ALL!$C$2:$C$341,ALL!L$2:L$341),"") | L26: =IF(_xlfn.XLOOKUP($C26,ALL!$C$2:$C$341,ALL!M$2:M$341)<>"",_xlfn.XLOOKUP($C26,ALL!$C$2:$C$341,ALL!M$2:M$341),"") | ... N26: =IF(_xlfn.XLOOKUP($C26,ALL!$C$2:$C$341,ALL!O$2:O$341)<>"",_xlfn.XLOOKUP($C26,ALL!$C$2:$C$341,ALL!O$2:O$341),"")
A27: =IF(_xlfn.XLOOKUP($C27,ALL!$C$2:$C$341,ALL!A$2:A$341)<>"",_xlfn.XLOOKUP($C27,ALL!$C$2:$C$341,ALL!A$2:A$341),"") | B27: =IF(_xlfn.XLOOKUP($C27,ALL!$C$2:$C$341,ALL!B$2:B$341)<>"",_xlfn.XLOOKUP($C27,ALL!$C$2:$C$341,ALL!B$2:B$341),"") | D27: =IF(_xlfn.XLOOKUP($C27,ALL!$C$2:$C$341,ALL!D$2:D$341)<>"",_xlfn.XLOOKUP($C27,ALL!$C$2:$C$341,ALL!D$2:D$341),"") | E27: =IF(_xlfn.XLOOKUP($C27,ALL!$C$2:$C$341,ALL!F$2:F$341)<>"",_xlfn.XLOOKUP($C27,ALL!$C$2:$C$341,ALL!F$2:F$341),"") | F27: =IF(_xlfn.XLOOKUP($C27,ALL!$C$2:$C$341,ALL!G$2:G$341)<>"",_xlfn.XLOOKUP($C27,ALL!$C$2:$C$341,ALL!G$2:G$341),"") | G27: =IF(_xlfn.XLOOKUP($C27,ALL!$C$2:$C$341,ALL!H$2:H$341)<>"",_xlfn.XLOOKUP($C27,ALL!$C$2:$C$341,ALL!H$2:H$341),"") | H27: =IF(_xlfn.XLOOKUP($C27,ALL!$C$2:$C$341,ALL!I$2:I$341)<>"",_xlfn.XLOOKUP($C27,ALL!$C$2:$C$341,ALL!I$2:I$341),"") | I27: =IF(_xlfn.XLOOKUP($C27,ALL!$C$2:$C$341,ALL!J$2:J$341)<>"",_xlfn.XLOOKUP($C27,ALL!$C$2:$C$341,ALL!J$2:J$341),"") | J27: =IF(_xlfn.XLOOKUP($C27,ALL!$C$2:$C$341,ALL!K$2:K$341)<>"",_xlfn.XLOOKUP($C27,ALL!$C$2:$C$341,ALL!K$2:K$341),"") | K27: =IF(_xlfn.XLOOKUP($C27,ALL!$C$2:$C$341,ALL!L$2:L$341)<>"",_xlfn.XLOOKUP($C27,ALL!$C$2:$C$341,ALL!L$2:L$341),"") | L27: =IF(_xlfn.XLOOKUP($C27,ALL!$C$2:$C$341,ALL!M$2:M$341)<>"",_xlfn.XLOOKUP($C27,ALL!$C$2:$C$341,ALL!M$2:M$341),"") | ... N27: =IF(_xlfn.XLOOKUP($C27,ALL!$C$2:$C$341,ALL!O$2:O$341)<>"",_xlfn.XLOOKUP($C27,ALL!$C$2:$C$341,ALL!O$2:O$341),"")
A28: =IF(_xlfn.XLOOKUP($C28,ALL!$C$2:$C$341,ALL!A$2:A$341)<>"",_xlfn.XLOOKUP($C28,ALL!$C$2:$C$341,ALL!A$2:A$341),"") | B28: =IF(_xlfn.XLOOKUP($C28,ALL!$C$2:$C$341,ALL!B$2:B$341)<>"",_xlfn.XLOOKUP($C28,ALL!$C$2:$C$341,ALL!B$2:B$341),"") | D28: =IF(_xlfn.XLOOKUP($C28,ALL!$C$2:$C$341,ALL!D$2:D$341)<>"",_xlfn.XLOOKUP($C28,ALL!$C$2:$C$341,ALL!D$2:D$341),"") | E28: =IF(_xlfn.XLOOKUP($C28,ALL!$C$2:$C$341,ALL!F$2:F$341)<>"",_xlfn.XLOOKUP($C28,ALL!$C$2:$C$341,ALL!F$2:F$341),"") | F28: =IF(_xlfn.XLOOKUP($C28,ALL!$C$2:$C$341,ALL!G$2:G$341)<>"",_xlfn.XLOOKUP($C28,ALL!$C$2:$C$341,ALL!G$2:G$341),"") | G28: =IF(_xlfn.XLOOKUP($C28,ALL!$C$2:$C$341,ALL!H$2:H$341)<>"",_xlfn.XLOOKUP($C28,ALL!$C$2:$C$341,ALL!H$2:H$341),"") | H28: =IF(_xlfn.XLOOKUP($C28,ALL!$C$2:$C$341,ALL!I$2:I$341)<>"",_xlfn.XLOOKUP($C28,ALL!$C$2:$C$341,ALL!I$2:I$341),"") | I28: =IF(_xlfn.XLOOKUP($C28,ALL!$C$2:$C$341,ALL!J$2:J$341)<>"",_xlfn.XLOOKUP($C28,ALL!$C$2:$C$341,ALL!J$2:J$341),"") | J28: =IF(_xlfn.XLOOKUP($C28,ALL!$C$2:$C$341,ALL!K$2:K$341)<>"",_xlfn.XLOOKUP($C28,ALL!$C$2:$C$341,ALL!K$2:K$341),"") | K28: =IF(_xlfn.XLOOKUP($C28,ALL!$C$2:$C$341,ALL!L$2:L$341)<>"",_xlfn.XLOOKUP($C28,ALL!$C$2:$C$341,ALL!L$2:L$341),"") | L28: =IF(_xlfn.XLOOKUP($C28,ALL!$C$2:$C$341,ALL!M$2:M$341)<>"",_xlfn.XLOOKUP($C28,ALL!$C$2:$C$341,ALL!M$2:M$341),"") | ... N28: =IF(_xlfn.XLOOKUP($C28,ALL!$C$2:$C$341,ALL!O$2:O$341)<>"",_xlfn.XLOOKUP($C28,ALL!$C$2:$C$341,ALL!O$2:O$341),"")
... A43: =IF(_xlfn.XLOOKUP($C43,ALL!$C$2:$C$341,ALL!A$2:A$341)<>"",_xlfn.XLOOKUP($C43,ALL!$C$2:$C$341,ALL!A$2:A$341),"") | B43: =IF(_xlfn.XLOOKUP($C43,ALL!$C$2:$C$341,ALL!B$2:B$341)<>"",_xlfn.XLOOKUP($C43,ALL!$C$2:$C$341,ALL!B$2:B$341),"") | D43: =IF(_xlfn.XLOOKUP($C43,ALL!$C$2:$C$341,ALL!D$2:D$341)<>"",_xlfn.XLOOKUP($C43,ALL!$C$2:$C$341,ALL!D$2:D$341),"") | E43: =IF(_xlfn.XLOOKUP($C43,ALL!$C$2:$C$341,ALL!F$2:F$341)<>"",_xlfn.XLOOKUP($C43,ALL!$C$2:$C$341,ALL!F$2:F$341),"") | F43: =IF(_xlfn.XLOOKUP($C43,ALL!$C$2:$C$341,ALL!G$2:G$341)<>"",_xlfn.XLOOKUP($C43,ALL!$C$2:$C$341,ALL!G$2:G$341),"") | G43: =IF(_xlfn.XLOOKUP($C43,ALL!$C$2:$C$341,ALL!H$2:H$341)<>"",_xlfn.XLOOKUP($C43,ALL!$C$2:$C$341,ALL!H$2:H$341),"") | H43: =IF(_xlfn.XLOOKUP($C43,ALL!$C$2:$C$341,ALL!I$2:I$341)<>"",_xlfn.XLOOKUP($C43,ALL!$C$2:$C$341,ALL!I$2:I$341),"") | I43: =IF(_xlfn.XLOOKUP($C43,ALL!$C$2:$C$341,ALL!J$2:J$341)<>"",_xlfn.XLOOKUP($C43,ALL!$C$2:$C$341,ALL!J$2:J$341),"") | J43: =IF(_xlfn.XLOOKUP($C43,ALL!$C$2:$C$341,ALL!K$2:K$341)<>"",_xlfn.XLOOKUP($C43,ALL!$C$2:$C$341,ALL!K$2:K$341),"") | K43: =IF(_xlfn.XLOOKUP($C43,ALL!$C$2:$C$341,ALL!L$2:L$341)<>"",_xlfn.XLOOKUP($C43,ALL!$C$2:$C$341,ALL!L$2:L$341),"") | L43: =IF(_xlfn.XLOOKUP($C43,ALL!$C$2:$C$341,ALL!M$2:M$341)<>"",_xlfn.XLOOKUP($C43,ALL!$C$2:$C$341,ALL!M$2:M$341),"") | ... N43: =IF(_xlfn.XLOOKUP($C43,ALL!$C$2:$C$341,ALL!O$2:O$341)<>"",_xlfn.XLOOKUP($C43,ALL!$C$2:$C$341,ALL!O$2:O$341),"")
A44: =IF(C44="","",($A$1-G44)-365) | B44: =IF(_xlfn.XLOOKUP($C44,ALL!$C$2:$C$341,ALL!B$2:B$341)<>"",_xlfn.XLOOKUP($C44,ALL!$C$2:$C$341,ALL!B$2:B$341),"") | D44: =IF(_xlfn.XLOOKUP($C44,ALL!$C$2:$C$341,ALL!D$2:D$341)<>"",_xlfn.XLOOKUP($C44,ALL!$C$2:$C$341,ALL!D$2:D$341),"") | E44: =IF(_xlfn.XLOOKUP($C44,ALL!$C$2:$C$341,ALL!F$2:F$341)<>"",_xlfn.XLOOKUP($C44,ALL!$C$2:$C$341,ALL!F$2:F$341),"") | F44: =IF(_xlfn.XLOOKUP($C44,ALL!$C$2:$C$341,ALL!G$2:G$341)<>"",_xlfn.XLOOKUP($C44,ALL!$C$2:$C$341,ALL!G$2:G$341),"") | G44: =IF(_xlfn.XLOOKUP($C44,ALL!$C$2:$C$341,ALL!H$2:H$341)<>"",_xlfn.XLOOKUP($C44,ALL!$C$2:$C$341,ALL!H$2:H$341),"") | H44: =IF(_xlfn.XLOOKUP($C44,ALL!$C$2:$C$341,ALL!I$2:I$341)<>"",_xlfn.XLOOKUP($C44,ALL!$C$2:$C$341,ALL!I$2:I$341),"") | I44: =IF(_xlfn.XLOOKUP($C44,ALL!$C$2:$C$341,ALL!J$2:J$341)<>"",_xlfn.XLOOKUP($C44,ALL!$C$2:$C$341,ALL!J$2:J$341),"") | J44: =IF(_xlfn.XLOOKUP($C44,ALL!$C$2:$C$341,ALL!K$2:K$341)<>"",_xlfn.XLOOKUP($C44,ALL!$C$2:$C$341,ALL!K$2:K$341),"") | K44: =IF(_xlfn.XLOOKUP($C44,ALL!$C$2:$C$341,ALL!L$2:L$341)<>"",_xlfn.XLOOKUP($C44,ALL!$C$2:$C$341,ALL!L$2:L$341),"") | L44: =IF(_xlfn.XLOOKUP($C44,ALL!$C$2:$C$341,ALL!M$2:M$341)<>"",_xlfn.XLOOKUP($C44,ALL!$C$2:$C$341,ALL!M$2:M$341),"") | M44: =IF(_xlfn.XLOOKUP($C44,ALL!$C$2:$C$341,ALL!N$2:N$341)<>"",_xlfn.XLOOKUP($C44,ALL!$C$2:$C$341,ALL!N$2:N$341),"")
A45: =IF(C45="","",($A$1-G45)-365) | B45: =IF(_xlfn.XLOOKUP($C45,ALL!$C$2:$C$341,ALL!B$2:B$341)<>"",_xlfn.XLOOKUP($C45,ALL!$C$2:$C$341,ALL!B$2:B$341),"") | D45: =IF(_xlfn.XLOOKUP($C45,ALL!$C$2:$C$341,ALL!D$2:D$341)<>"",_xlfn.XLOOKUP($C45,ALL!$C$2:$C$341,ALL!D$2:D$341),"") | E45: =IF(_xlfn.XLOOKUP($C45,ALL!$C$2:$C$341,ALL!F$2:F$341)<>"",_xlfn.XLOOKUP($C45,ALL!$C$2:$C$341,ALL!F$2:F$341),"") | F45: =IF(_xlfn.XLOOKUP($C45,ALL!$C$2:$C$341,ALL!G$2:G$341)<>"",_xlfn.XLOOKUP($C45,ALL!$C$2:$C$341,ALL!G$2:G$341),"") | G45: =IF(_xlfn.XLOOKUP($C45,ALL!$C$2:$C$341,ALL!H$2:H$341)<>"",_xlfn.XLOOKUP($C45,ALL!$C$2:$C$341,ALL!H$2:H$341),"") | H45: =IF(_xlfn.XLOOKUP($C45,ALL!$C$2:$C$341,ALL!I$2:I$341)<>"",_xlfn.XLOOKUP($C45,ALL!$C$2:$C$341,ALL!I$2:I$341),"") | I45: =IF(_xlfn.XLOOKUP($C45,ALL!$C$2:$C$341,ALL!J$2:J$341)<>"",_xlfn.XLOOKUP($C45,ALL!$C$2:$C$341,ALL!J$2:J$341),"") | J45: =IF(_xlfn.XLOOKUP($C45,ALL!$C$2:$C$341,ALL!K$2:K$341)<>"",_xlfn.XLOOKUP($C45,ALL!$C$2:$C$341,ALL!K$2:K$341),"") | K45: =IF(_xlfn.XLOOKUP($C45,ALL!$C$2:$C$341,ALL!L$2:L$341)<>"",_xlfn.XLOOKUP($C45,ALL!$C$2:$C$341,ALL!L$2:L$341),"") | L45: =IF(_xlfn.XLOOKUP($C45,ALL!$C$2:$C$341,ALL!M$2:M$341)<>"",_xlfn.XLOOKUP($C45,ALL!$C$2:$C$341,ALL!M$2:M$341),"") | M45: =IF(_xlfn.XLOOKUP($C45,ALL!$C$2:$C$341,ALL!N$2:N$341)<>"",_xlfn.XLOOKUP($C45,ALL!$C$2:$C$341,ALL!N$2:N$341),"")
A46: =IF(C46="","",($A$1-G46)-365) | B46: =IF(_xlfn.XLOOKUP($C46,ALL!$C$2:$C$341,ALL!B$2:B$341)<>"",_xlfn.XLOOKUP($C46,ALL!$C$2:$C$341,ALL!B$2:B$341),"") | D46: =IF(_xlfn.XLOOKUP($C46,ALL!$C$2:$C$341,ALL!D$2:D$341)<>"",_xlfn.XLOOKUP($C46,ALL!$C$2:$C$341,ALL!D$2:D$341),"") | E46: =IF(_xlfn.XLOOKUP($C46,ALL!$C$2:$C$341,ALL!F$2:F$341)<>"",_xlfn.XLOOKUP($C46,ALL!$C$2:$C$341,ALL!F$2:F$341),"") | F46: =IF(_xlfn.XLOOKUP($C46,ALL!$C$2:$C$341,ALL!G$2:G$341)<>"",_xlfn.XLOOKUP($C46,ALL!$C$2:$C$341,ALL!G$2:G$341),"") | G46: =IF(_xlfn.XLOOKUP($C46,ALL!$C$2:$C$341,ALL!H$2:H$341)<>"",_xlfn.XLOOKUP($C46,ALL!$C$2:$C$341,ALL!H$2:H$341),"") | H46: =IF(_xlfn.XLOOKUP($C46,ALL!$C$2:$C$341,ALL!I$2:I$341)<>"",_xlfn.XLOOKUP($C46,ALL!$C$2:$C$341,ALL!I$2:I$341),"") | I46: =IF(_xlfn.XLOOKUP($C46,ALL!$C$2:$C$341,ALL!J$2:J$341)<>"",_xlfn.XLOOKUP($C46,ALL!$C$2:$C$341,ALL!J$2:J$341),"") | J46: =IF(_xlfn.XLOOKUP($C46,ALL!$C$2:$C$341,ALL!K$2:K$341)<>"",_xlfn.XLOOKUP($C46,ALL!$C$2:$C$341,ALL!K$2:K$341),"") | K46: =IF(_xlfn.XLOOKUP($C46,ALL!$C$2:$C$341,ALL!L$2:L$341)<>"",_xlfn.XLOOKUP($C46,ALL!$C$2:$C$341,ALL!L$2:L$341),"") | L46: =IF(_xlfn.XLOOKUP($C46,ALL!$C$2:$C$341,ALL!M$2:M$341)<>"",_xlfn.XLOOKUP($C46,ALL!$C$2:$C$341,ALL!M$2:M$341),"") | M46: =IF(_xlfn.XLOOKUP($C46,ALL!$C$2:$C$341,ALL!N$2:N$341)<>"",_xlfn.XLOOKUP($C46,ALL!$C$2:$C$341,ALL!N$2:N$341),"")
A47: =IF(C47="","",($A$1-G47)-365) | B47: =IF(_xlfn.XLOOKUP($C47,ALL!$C$2:$C$341,ALL!B$2:B$341)<>"",_xlfn.XLOOKUP($C47,ALL!$C$2:$C$341,ALL!B$2:B$341),"") | D47: =IF(_xlfn.XLOOKUP($C47,ALL!$C$2:$C$341,ALL!D$2:D$341)<>"",_xlfn.XLOOKUP($C47,ALL!$C$2:$C$341,ALL!D$2:D$341),"") | E47: =IF(_xlfn.XLOOKUP($C47,ALL!$C$2:$C$341,ALL!F$2:F$341)<>"",_xlfn.XLOOKUP($C47,ALL!$C$2:$C$341,ALL!F$2:F$341),"") | F47: =IF(_xlfn.XLOOKUP($C47,ALL!$C$2:$C$341,ALL!G$2:G$341)<>"",_xlfn.XLOOKUP($C47,ALL!$C$2:$C$341,ALL!G$2:G$341),"") | G47: =IF(_xlfn.XLOOKUP($C47,ALL!$C$2:$C$341,ALL!H$2:H$341)<>"",_xlfn.XLOOKUP($C47,ALL!$C$2:$C$341,ALL!H$2:H$341),"") | H47: =IF(_xlfn.XLOOKUP($C47,ALL!$C$2:$C$341,ALL!I$2:I$341)<>"",_xlfn.XLOOKUP($C47,ALL!$C$2:$C$341,ALL!I$2:I$341),"") | I47: =IF(_xlfn.XLOOKUP($C47,ALL!$C$2:$C$341,ALL!J$2:J$341)<>"",_xlfn.XLOOKUP($C47,ALL!$C$2:$C$341,ALL!J$2:J$341),"") | J47: =IF(_xlfn.XLOOKUP($C47,ALL!$C$2:$C$341,ALL!K$2:K$341)<>"",_xlfn.XLOOKUP($C47,ALL!$C$2:$C$341,ALL!K$2:K$341),"") | K47: =IF(_xlfn.XLOOKUP($C47,ALL!$C$2:$C$341,ALL!L$2:L$341)<>"",_xlfn.XLOOKUP($C47,ALL!$C$2:$C$341,ALL!L$2:L$341),"") | L47: =IF(_xlfn.XLOOKUP($C47,ALL!$C$2:$C$341,ALL!M$2:M$341)<>"",_xlfn.XLOOKUP($C47,ALL!$C$2:$C$341,ALL!M$2:M$341),"") | M47: =IF(_xlfn.XLOOKUP($C47,ALL!$C$2:$C$341,ALL!N$2:N$341)<>"",_xlfn.XLOOKUP($C47,ALL!$C$2:$C$341,ALL!N$2:N$341),"")
A48: =IF(C48="","",($A$1-G48)-365) | B48: =IF(_xlfn.XLOOKUP($C48,ALL!$C$2:$C$341,ALL!B$2:B$341)<>"",_xlfn.XLOOKUP($C48,ALL!$C$2:$C$341,ALL!B$2:B$341),"") | D48: =IF(_xlfn.XLOOKUP($C48,ALL!$C$2:$C$341,ALL!D$2:D$341)<>"",_xlfn.XLOOKUP($C48,ALL!$C$2:$C$341,ALL!D$2:D$341),"") | E48: =IF(_xlfn.XLOOKUP($C48,ALL!$C$2:$C$341,ALL!F$2:F$341)<>"",_xlfn.XLOOKUP($C48,ALL!$C$2:$C$341,ALL!F$2:F$341),"") | F48: =IF(_xlfn.XLOOKUP($C48,ALL!$C$2:$C$341,ALL!G$2:G$341)<>"",_xlfn.XLOOKUP($C48,ALL!$C$2:$C$341,ALL!G$2:G$341),"") | G48: =IF(_xlfn.XLOOKUP($C48,ALL!$C$2:$C$341,ALL!H$2:H$341)<>"",_xlfn.XLOOKUP($C48,ALL!$C$2:$C$341,ALL!H$2:H$341),"") | H48: =IF(_xlfn.XLOOKUP($C48,ALL!$C$2:$C$341,ALL!I$2:I$341)<>"",_xlfn.XLOOKUP($C48,ALL!$C$2:$C$341,ALL!I$2:I$341),"") | I48: =IF(_xlfn.XLOOKUP($C48,ALL!$C$2:$C$341,ALL!J$2:J$341)<>"",_xlfn.XLOOKUP($C48,ALL!$C$2:$C$341,ALL!J$2:J$341),"") | J48: =IF(_xlfn.XLOOKUP($C48,ALL!$C$2:$C$341,ALL!K$2:K$341)<>"",_xlfn.XLOOKUP($C48,ALL!$C$2:$C$341,ALL!K$2:K$341),"") | K48: =IF(_xlfn.XLOOKUP($C48,ALL!$C$2:$C$341,ALL!L$2:L$341)<>"",_xlfn.XLOOKUP($C48,ALL!$C$2:$C$341,ALL!L$2:L$341),"") | L48: =IF(_xlfn.XLOOKUP($C48,ALL!$C$2:$C$341,ALL!M$2:M$341)<>"",_xlfn.XLOOKUP($C48,ALL!$C$2:$C$341,ALL!M$2:M$341),"") | M48: =IF(_xlfn.XLOOKUP($C48,ALL!$C$2:$C$341,ALL!N$2:N$341)<>"",_xlfn.XLOOKUP($C48,ALL!$C$2:$C$341,ALL!N$2:N$341),"")
A49: =IF(C49="","",($A$1-G49)-365) | B49: =IF(_xlfn.XLOOKUP($C49,ALL!$C$2:$C$341,ALL!B$2:B$341)<>"",_xlfn.XLOOKUP($C49,ALL!$C$2:$C$341,ALL!B$2:B$341),"") | D49: =IF(_xlfn.XLOOKUP($C49,ALL!$C$2:$C$341,ALL!D$2:D$341)<>"",_xlfn.XLOOKUP($C49,ALL!$C$2:$C$341,ALL!D$2:D$341),"") | E49: =IF(_xlfn.XLOOKUP($C49,ALL!$C$2:$C$341,ALL!F$2:F$341)<>"",_xlfn.XLOOKUP($C49,ALL!$C$2:$C$341,ALL!F$2:F$341),"") | F49: =IF(_xlfn.XLOOKUP($C49,ALL!$C$2:$C$341,ALL!G$2:G$341)<>"",_xlfn.XLOOKUP($C49,ALL!$C$2:$C$341,ALL!G$2:G$341),"") | G49: =IF(_xlfn.XLOOKUP($C49,ALL!$C$2:$C$341,ALL!H$2:H$341)<>"",_xlfn.XLOOKUP($C49,ALL!$C$2:$C$341,ALL!H$2:H$341),"") | H49: =IF(_xlfn.XLOOKUP($C49,ALL!$C$2:$C$341,ALL!I$2:I$341)<>"",_xlfn.XLOOKUP($C49,ALL!$C$2:$C$341,ALL!I$2:I$341),"") | I49: =IF(_xlfn.XLOOKUP($C49,ALL!$C$2:$C$341,ALL!J$2:J$341)<>"",_xlfn.XLOOKUP($C49,ALL!$C$2:$C$341,ALL!J$2:J$341),"") | J49: =IF(_xlfn.XLOOKUP($C49,ALL!$C$2:$C$341,ALL!K$2:K$341)<>"",_xlfn.XLOOKUP($C49,ALL!$C$2:$C$341,ALL!K$2:K$341),"") | K49: =IF(_xlfn.XLOOKUP($C49,ALL!$C$2:$C$341,ALL!L$2:L$341)<>"",_xlfn.XLOOKUP($C49,ALL!$C$2:$C$341,ALL!L$2:L$341),"") | L49: =IF(_xlfn.XLOOKUP($C49,ALL!$C$2:$C$341,ALL!M$2:M$341)<>"",_xlfn.XLOOKUP($C49,ALL!$C$2:$C$341,ALL!M$2:M$341),"") | M49: =IF(_xlfn.XLOOKUP($C49,ALL!$C$2:$C$341,ALL!N$2:N$341)<>"",_xlfn.XLOOKUP($C49,ALL!$C$2:$C$341,ALL!N$2:N$341),"")
A50: =IF(C50="","",($A$1-G50)-365) | B50: =IF(_xlfn.XLOOKUP($C50,ALL!$C$2:$C$341,ALL!B$2:B$341)<>"",_xlfn.XLOOKUP($C50,ALL!$C$2:$C$341,ALL!B$2:B$341),"") | D50: =IF(_xlfn.XLOOKUP($C50,ALL!$C$2:$C$341,ALL!D$2:D$341)<>"",_xlfn.XLOOKUP($C50,ALL!$C$2:$C$341,ALL!D$2:D$341),"") | E50: =IF(_xlfn.XLOOKUP($C50,ALL!$C$2:$C$341,ALL!F$2:F$341)<>"",_xlfn.XLOOKUP($C50,ALL!$C$2:$C$341,ALL!F$2:F$341),"") | F50: =IF(_xlfn.XLOOKUP($C50,ALL!$C$2:$C$341,ALL!G$2:G$341)<>"",_xlfn.XLOOKUP($C50,ALL!$C$2:$C$341,ALL!G$2:G$341),"") | G50: =IF(_xlfn.XLOOKUP($C50,ALL!$C$2:$C$341,ALL!H$2:H$341)<>"",_xlfn.XLOOKUP($C50,ALL!$C$2:$C$341,ALL!H$2:H$341),"") | H50: =IF(_xlfn.XLOOKUP($C50,ALL!$C$2:$C$341,ALL!I$2:I$341)<>"",_xlfn.XLOOKUP($C50,ALL!$C$2:$C$341,ALL!I$2:I$341),"") | I50: =IF(_xlfn.XLOOKUP($C50,ALL!$C$2:$C$341,ALL!J$2:J$341)<>"",_xlfn.XLOOKUP($C50,ALL!$C$2:$C$341,ALL!J$2:J$341),"") | J50: =IF(_xlfn.XLOOKUP($C50,ALL!$C$2:$C$341,ALL!K$2:K$341)<>"",_xlfn.XLOOKUP($C50,ALL!$C$2:$C$341,ALL!K$2:K$341),"") | K50: =IF(_xlfn.XLOOKUP($C50,ALL!$C$2:$C$341,ALL!L$2:L$341)<>"",_xlfn.XLOOKUP($C50,ALL!$C$2:$C$341,ALL!L$2:L$341),"") | L50: =IF(_xlfn.XLOOKUP($C50,ALL!$C$2:$C$341,ALL!M$2:M$341)<>"",_xlfn.XLOOKUP($C50,ALL!$C$2:$C$341,ALL!M$2:M$341),"") | M50: =IF(_xlfn.XLOOKUP($C50,ALL!$C$2:$C$341,ALL!N$2:N$341)<>"",_xlfn.XLOOKUP($C50,ALL!$C$2:$C$341,ALL!N$2:N$341),"")
A51: =IF(C51="","",($A$1-G51)-365) | B51: =IF(_xlfn.XLOOKUP($C51,ALL!$C$2:$C$341,ALL!B$2:B$341)<>"",_xlfn.XLOOKUP($C51,ALL!$C$2:$C$341,ALL!B$2:B$341),"") | D51: =IF(_xlfn.XLOOKUP($C51,ALL!$C$2:$C$341,ALL!D$2:D$341)<>"",_xlfn.XLOOKUP($C51,ALL!$C$2:$C$341,ALL!D$2:D$341),"") | E51: =IF(_xlfn.XLOOKUP($C51,ALL!$C$2:$C$341,ALL!F$2:F$341)<>"",_xlfn.XLOOKUP($C51,ALL!$C$2:$C$341,ALL!F$2:F$341),"") | F51: =IF(_xlfn.XLOOKUP($C51,ALL!$C$2:$C$341,ALL!G$2:G$341)<>"",_xlfn.XLOOKUP($C51,ALL!$C$2:$C$341,ALL!G$2:G$341),"") | G51: =IF(_xlfn.XLOOKUP($C51,ALL!$C$2:$C$341,ALL!H$2:H$341)<>"",_xlfn.XLOOKUP($C51,ALL!$C$2:$C$341,ALL!H$2:H$341),"") | H51: =IF(_xlfn.XLOOKUP($C51,ALL!$C$2:$C$341,ALL!I$2:I$341)<>"",_xlfn.XLOOKUP($C51,ALL!$C$2:$C$341,ALL!I$2:I$341),"") | I51: =IF(_xlfn.XLOOKUP($C51,ALL!$C$2:$C$341,ALL!J$2:J$341)<>"",_xlfn.XLOOKUP($C51,ALL!$C$2:$C$341,ALL!J$2:J$341),"") | J51: =IF(_xlfn.XLOOKUP($C51,ALL!$C$2:$C$341,ALL!K$2:K$341)<>"",_xlfn.XLOOKUP($C51,ALL!$C$2:$C$341,ALL!K$2:K$341),"") | K51: =IF(_xlfn.XLOOKUP($C51,ALL!$C$2:$C$341,ALL!L$2:L$341)<>"",_xlfn.XLOOKUP($C51,ALL!$C$2:$C$341,ALL!L$2:L$341),"") | L51: =IF(_xlfn.XLOOKUP($C51,ALL!$C$2:$C$341,ALL!M$2:M$341)<>"",_xlfn.XLOOKUP($C51,ALL!$C$2:$C$341,ALL!M$2:M$341),"") | M51: =IF(_xlfn.XLOOKUP($C51,ALL!$C$2:$C$341,ALL!N$2:N$341)<>"",_xlfn.XLOOKUP($C51,ALL!$C$2:$C$341,ALL!N$2:N$341),"")
A52: =IF(C52="","",($A$1-G52)-365) | B52: =IF(_xlfn.XLOOKUP($C52,ALL!$C$2:$C$341,ALL!B$2:B$341)<>"",_xlfn.XLOOKUP($C52,ALL!$C$2:$C$341,ALL!B$2:B$341),"") | D52: =IF(_xlfn.XLOOKUP($C52,ALL!$C$2:$C$341,ALL!D$2:D$341)<>"",_xlfn.XLOOKUP($C52,ALL!$C$2:$C$341,ALL!D$2:D$341),"") | E52: =IF(_xlfn.XLOOKUP($C52,ALL!$C$2:$C$341,ALL!F$2:F$341)<>"",_xlfn.XLOOKUP($C52,ALL!$C$2:$C$341,ALL!F$2:F$341),"") | F52: =IF(_xlfn.XLOOKUP($C52,ALL!$C$2:$C$341,ALL!G$2:G$341)<>"",_xlfn.XLOOKUP($C52,ALL!$C$2:$C$341,ALL!G$2:G$341),"") | G52: =IF(_xlfn.XLOOKUP($C52,ALL!$C$2:$C$341,ALL!H$2:H$341)<>"",_xlfn.XLOOKUP($C52,ALL!$C$2:$C$341,ALL!H$2:H$341),"") | H52: =IF(_xlfn.XLOOKUP($C52,ALL!$C$2:$C$341,ALL!I$2:I$341)<>"",_xlfn.XLOOKUP($C52,ALL!$C$2:$C$341,ALL!I$2:I$341),"") | I52: =IF(_xlfn.XLOOKUP($C52,ALL!$C$2:$C$341,ALL!J$2:J$341)<>"",_xlfn.XLOOKUP($C52,ALL!$C$2:$C$341,ALL!J$2:J$341),"") | J52: =IF(_xlfn.XLOOKUP($C52,ALL!$C$2:$C$341,ALL!K$2:K$341)<>"",_xlfn.XLOOKUP($C52,ALL!$C$2:$C$341,ALL!K$2:K$341),"") | K52: =IF(_xlfn.XLOOKUP($C52,ALL!$C$2:$C$341,ALL!L$2:L$341)<>"",_xlfn.XLOOKUP($C52,ALL!$C$2:$C$341,ALL!L$2:L$341),"") | L52: =IF(_xlfn.XLOOKUP($C52,ALL!$C$2:$C$341,ALL!M$2:M$341)<>"",_xlfn.XLOOKUP($C52,ALL!$C$2:$C$341,ALL!M$2:M$341),"") | M52: =IF(_xlfn.XLOOKUP($C52,ALL!$C$2:$C$341,ALL!N$2:N$341)<>"",_xlfn.XLOOKUP($C52,ALL!$C$2:$C$341,ALL!N$2:N$341),"")
A53: =IF(C53="","",($A$1-G53)-365) | B53: =IF(_xlfn.XLOOKUP($C53,ALL!$C$2:$C$341,ALL!B$2:B$341)<>"",_xlfn.XLOOKUP($C53,ALL!$C$2:$C$341,ALL!B$2:B$341),"") | D53: =IF(_xlfn.XLOOKUP($C53,ALL!$C$2:$C$341,ALL!D$2:D$341)<>"",_xlfn.XLOOKUP($C53,ALL!$C$2:$C$341,ALL!D$2:D$341),"") | E53: =IF(_xlfn.XLOOKUP($C53,ALL!$C$2:$C$341,ALL!F$2:F$341)<>"",_xlfn.XLOOKUP($C53,ALL!$C$2:$C$341,ALL!F$2:F$341),"") | F53: =IF(_xlfn.XLOOKUP($C53,ALL!$C$2:$C$341,ALL!G$2:G$341)<>"",_xlfn.XLOOKUP($C53,ALL!$C$2:$C$341,ALL!G$2:G$341),"") | G53: =IF(_xlfn.XLOOKUP($C53,ALL!$C$2:$C$341,ALL!H$2:H$341)<>"",_xlfn.XLOOKUP($C53,ALL!$C$2:$C$341,ALL!H$2:H$341),"") | H53: =IF(_xlfn.XLOOKUP($C53,ALL!$C$2:$C$341,ALL!I$2:I$341)<>"",_xlfn.XLOOKUP($C53,ALL!$C$2:$C$341,ALL!I$2:I$341),"") | I53: =IF(_xlfn.XLOOKUP($C53,ALL!$C$2:$C$341,ALL!J$2:J$341)<>"",_xlfn.XLOOKUP($C53,ALL!$C$2:$C$341,ALL!J$2:J$341),"") | J53: =IF(_xlfn.XLOOKUP($C53,ALL!$C$2:$C$341,ALL!K$2:K$341)<>"",_xlfn.XLOOKUP($C53,ALL!$C$2:$C$341,ALL!K$2:K$341),"") | K53: =IF(_xlfn.XLOOKUP($C53,ALL!$C$2:$C$341,ALL!L$2:L$341)<>"",_xlfn.XLOOKUP($C53,ALL!$C$2:$C$341,ALL!L$2:L$341),"") | L53: =IF(_xlfn.XLOOKUP($C53,ALL!$C$2:$C$341,ALL!M$2:M$341)<>"",_xlfn.XLOOKUP($C53,ALL!$C$2:$C$341,ALL!M$2:M$341),"") | M53: =IF(_xlfn.XLOOKUP($C53,ALL!$C$2:$C$341,ALL!N$2:N$341)<>"",_xlfn.XLOOKUP($C53,ALL!$C$2:$C$341,ALL!N$2:N$341),"")
A54: =IF(C54="","",($A$1-G54)-365) | B54: =IF(_xlfn.XLOOKUP($C54,ALL!$C$2:$C$341,ALL!B$2:B$341)<>"",_xlfn.XLOOKUP($C54,ALL!$C$2:$C$341,ALL!B$2:B$341),"") | D54: =IF(_xlfn.XLOOKUP($C54,ALL!$C$2:$C$341,ALL!D$2:D$341)<>"",_xlfn.XLOOKUP($C54,ALL!$C$2:$C$341,ALL!D$2:D$341),"") | E54: =IF(_xlfn.XLOOKUP($C54,ALL!$C$2:$C$341,ALL!F$2:F$341)<>"",_xlfn.XLOOKUP($C54,ALL!$C$2:$C$341,ALL!F$2:F$341),"") | F54: =IF(_xlfn.XLOOKUP($C54,ALL!$C$2:$C$341,ALL!G$2:G$341)<>"",_xlfn.XLOOKUP($C54,ALL!$C$2:$C$341,ALL!G$2:G$341),"") | G54: =IF(_xlfn.XLOOKUP($C54,ALL!$C$2:$C$341,ALL!H$2:H$341)<>"",_xlfn.XLOOKUP($C54,ALL!$C$2:$C$341,ALL!H$2:H$341),"") | H54: =IF(_xlfn.XLOOKUP($C54,ALL!$C$2:$C$341,ALL!I$2:I$341)<>"",_xlfn.XLOOKUP($C54,ALL!$C$2:$C$341,ALL!I$2:I$341),"") | I54: =IF(_xlfn.XLOOKUP($C54,ALL!$C$2:$C$341,ALL!J$2:J$341)<>"",_xlfn.XLOOKUP($C54,ALL!$C$2:$C$341,ALL!J$2:J$341),"") | J54: =IF(_xlfn.XLOOKUP($C54,ALL!$C$2:$C$341,ALL!K$2:K$341)<>"",_xlfn.XLOOKUP($C54,ALL!$C$2:$C$341,ALL!K$2:K$341),"") | K54: =IF(_xlfn.XLOOKUP($C54,ALL!$C$2:$C$341,ALL!L$2:L$341)<>"",_xlfn.XLOOKUP($C54,ALL!$C$2:$C$341,ALL!L$2:L$341),"") | L54: =IF(_xlfn.XLOOKUP($C54,ALL!$C$2:$C$341,ALL!M$2:M$341)<>"",_xlfn.XLOOKUP($C54,ALL!$C$2:$C$341,ALL!M$2:M$341),"") | M54: =IF(_xlfn.XLOOKUP($C54,ALL!$C$2:$C$341,ALL!N$2:N$341)<>"",_xlfn.XLOOKUP($C54,ALL!$C$2:$C$341,ALL!N$2:N$341),"")
A55: =IF(C55="","",($A$1-G55)-365) | B55: =IF(_xlfn.XLOOKUP($C55,ALL!$C$2:$C$341,ALL!B$2:B$341)<>"",_xlfn.XLOOKUP($C55,ALL!$C$2:$C$341,ALL!B$2:B$341),"") | D55: =IF(_xlfn.XLOOKUP($C55,ALL!$C$2:$C$341,ALL!D$2:D$341)<>"",_xlfn.XLOOKUP($C55,ALL!$C$2:$C$341,ALL!D$2:D$341),"") | E55: =IF(_xlfn.XLOOKUP($C55,ALL!$C$2:$C$341,ALL!F$2:F$341)<>"",_xlfn.XLOOKUP($C55,ALL!$C$2:$C$341,ALL!F$2:F$341),"") | F55: =IF(_xlfn.XLOOKUP($C55,ALL!$C$2:$C$341,ALL!G$2:G$341)<>"",_xlfn.XLOOKUP($C55,ALL!$C$2:$C$341,ALL!G$2:G$341),"") | G55: =IF(_xlfn.XLOOKUP($C55,ALL!$C$2:$C$341,ALL!H$2:H$341)<>"",_xlfn.XLOOKUP($C55,ALL!$C$2:$C$341,ALL!H$2:H$341),"") | H55: =IF(_xlfn.XLOOKUP($C55,ALL!$C$2:$C$341,ALL!I$2:I$341)<>"",_xlfn.XLOOKUP($C55,ALL!$C$2:$C$341,ALL!I$2:I$341),"") | I55: =IF(_xlfn.XLOOKUP($C55,ALL!$C$2:$C$341,ALL!J$2:J$341)<>"",_xlfn.XLOOKUP($C55,ALL!$C$2:$C$341,ALL!J$2:J$341),"") | J55: =IF(_xlfn.XLOOKUP($C55,ALL!$C$2:$C$341,ALL!K$2:K$341)<>"",_xlfn.XLOOKUP($C55,ALL!$C$2:$C$341,ALL!K$2:K$341),"") | K55: =IF(_xlfn.XLOOKUP($C55,ALL!$C$2:$C$341,ALL!L$2:L$341)<>"",_xlfn.XLOOKUP($C55,ALL!$C$2:$C$341,ALL!L$2:L$341),"") | L55: =IF(_xlfn.XLOOKUP($C55,ALL!$C$2:$C$341,ALL!M$2:M$341)<>"",_xlfn.XLOOKUP($C55,ALL!$C$2:$C$341,ALL!M$2:M$341),"") | M55: =IF(_xlfn.XLOOKUP($C55,ALL!$C$2:$C$341,ALL!N$2:N$341)<>"",_xlfn.XLOOKUP($C55,ALL!$C$2:$C$341,ALL!N$2:N$341),"")
... A154: =IF(C154="","",($A$1-G154)-365) | B154: =IF(_xlfn.XLOOKUP($C154,ALL!$C$2:$C$341,ALL!B$2:B$341)<>"",_xlfn.XLOOKUP($C154,ALL!$C$2:$C$341,ALL!B$2:B$341),"") | D154: =IF(_xlfn.XLOOKUP($C154,ALL!$C$2:$C$341,ALL!D$2:D$341)<>"",_xlfn.XLOOKUP($C154,ALL!$C$2:$C$341,ALL!D$2:D$341),"") | E154: =IF(_xlfn.XLOOKUP($C154,ALL!$C$2:$C$341,ALL!F$2:F$341)<>"",_xlfn.XLOOKUP($C154,ALL!$C$2:$C$341,ALL!F$2:F$341),"") | F154: =IF(_xlfn.XLOOKUP($C154,ALL!$C$2:$C$341,ALL!G$2:G$341)<>"",_xlfn.XLOOKUP($C154,ALL!$C$2:$C$341,ALL!G$2:G$341),"") | G154: =IF(_xlfn.XLOOKUP($C154,ALL!$C$2:$C$341,ALL!H$2:H$341)<>"",_xlfn.XLOOKUP($C154,ALL!$C$2:$C$341,ALL!H$2:H$341),"") | H154: =IF(_xlfn.XLOOKUP($C154,ALL!$C$2:$C$341,ALL!I$2:I$341)<>"",_xlfn.XLOOKUP($C154,ALL!$C$2:$C$341,ALL!I$2:I$341),"") | I154: =IF(_xlfn.XLOOKUP($C154,ALL!$C$2:$C$341,ALL!J$2:J$341)<>"",_xlfn.XLOOKUP($C154,ALL!$C$2:$C$341,ALL!J$2:J$341),"") | J154: =IF(_xlfn.XLOOKUP($C154,ALL!$C$2:$C$341,ALL!K$2:K$341)<>"",_xlfn.XLOOKUP($C154,ALL!$C$2:$C$341,ALL!K$2:K$341),"") | K154: =IF(_xlfn.XLOOKUP($C154,ALL!$C$2:$C$341,ALL!L$2:L$341)<>"",_xlfn.XLOOKUP($C154,ALL!$C$2:$C$341,ALL!L$2:L$341),"") | L154: =IF(_xlfn.XLOOKUP($C154,ALL!$C$2:$C$341,ALL!M$2:M$341)<>"",_xlfn.XLOOKUP($C154,ALL!$C$2:$C$341,ALL!M$2:M$341),"") | M154: =IF(_xlfn.XLOOKUP($C154,ALL!$C$2:$C$341,ALL!N$2:N$341)<>"",_xlfn.XLOOKUP($C154,ALL!$C$2:$C$341,ALL!N$2:N$341),"")
